{"config":{"output_file":null,"full_docs":false,"pub_only":true,"reachable_only":true,"distro_crate":false,"signatures":false,"borrow_data":false},"prelude":{"crate_id":{"name":"legv8_asm","disambiguator":[4586019999066586563,13650729294884938397]},"crate_root":"/home/tim/Rowan/Classes/ComputerArchitecture/legv8_asm/legv8_asm/src","external_crates":[{"file_name":"/home/tim/Rowan/Classes/ComputerArchitecture/legv8_asm/legv8_asm/src/lib.rs","num":1,"id":{"name":"std","disambiguator":[6340897705536774201,11881073841629916418]}},{"file_name":"/home/tim/Rowan/Classes/ComputerArchitecture/legv8_asm/legv8_asm/src/lib.rs","num":2,"id":{"name":"core","disambiguator":[9732377270468940789,1831871757255437960]}},{"file_name":"/home/tim/Rowan/Classes/ComputerArchitecture/legv8_asm/legv8_asm/src/lib.rs","num":3,"id":{"name":"alloc","disambiguator":[3268492434991643085,5589035544053813149]}},{"file_name":"/home/tim/Rowan/Classes/ComputerArchitecture/legv8_asm/legv8_asm/src/lib.rs","num":4,"id":{"name":"std_unicode","disambiguator":[2326178704002472276,9116190598109638507]}},{"file_name":"/home/tim/Rowan/Classes/ComputerArchitecture/legv8_asm/legv8_asm/src/lib.rs","num":5,"id":{"name":"alloc_system","disambiguator":[13442825029059366032,15807473255522138379]}},{"file_name":"/home/tim/Rowan/Classes/ComputerArchitecture/legv8_asm/legv8_asm/src/lib.rs","num":6,"id":{"name":"libc","disambiguator":[8553617812322560355,6302201041758426078]}},{"file_name":"/home/tim/Rowan/Classes/ComputerArchitecture/legv8_asm/legv8_asm/src/lib.rs","num":7,"id":{"name":"unwind","disambiguator":[2252714884481077449,14992585432713575026]}},{"file_name":"/home/tim/Rowan/Classes/ComputerArchitecture/legv8_asm/legv8_asm/src/lib.rs","num":8,"id":{"name":"compiler_builtins","disambiguator":[576367709554443321,4159597933567931188]}},{"file_name":"/home/tim/Rowan/Classes/ComputerArchitecture/legv8_asm/legv8_asm/src/lib.rs","num":9,"id":{"name":"alloc_jemalloc","disambiguator":[16250756884290876468,15909190426605280400]}},{"file_name":"/home/tim/Rowan/Classes/ComputerArchitecture/legv8_asm/legv8_asm/src/lib.rs","num":10,"id":{"name":"panic_unwind","disambiguator":[8539890582683856309,9111111243289024747]}},{"file_name":"/home/tim/Rowan/Classes/ComputerArchitecture/legv8_asm/legv8_asm/src/lib.rs","num":11,"id":{"name":"nom","disambiguator":[4884236485531107321,1493962833921003172]}},{"file_name":"/home/tim/Rowan/Classes/ComputerArchitecture/legv8_asm/legv8_asm/src/lib.rs","num":12,"id":{"name":"memchr","disambiguator":[11625989470660419130,4235133001965415879]}},{"file_name":"/home/tim/Rowan/Classes/ComputerArchitecture/legv8_asm/legv8_asm/src/lib.rs","num":13,"id":{"name":"libc","disambiguator":[17267137473536514775,8347247169132024386]}}],"span":{"file_name":[47,104,111,109,101,47,116,105,109,47,82,111,119,97,110,47,67,108,97,115,115,101,115,47,67,111,109,112,117,116,101,114,65,114,99,104,105,116,101,99,116,117,114,101,47,108,101,103,118,56,95,97,115,109,47,108,101,103,118,56,95,97,115,109,47,115,114,99,47,108,105,98,46,114,115],"byte_start":1,"byte_end":1584,"line_start":2,"line_end":71,"column_start":1,"column_end":2}},"imports":[],"defs":[{"kind":"Mod","id":{"krate":0,"index":0},"span":{"file_name":[47,104,111,109,101,47,116,105,109,47,82,111,119,97,110,47,67,108,97,115,115,101,115,47,67,111,109,112,117,116,101,114,65,114,99,104,105,116,101,99,116,117,114,101,47,108,101,103,118,56,95,97,115,109,47,108,101,103,118,56,95,97,115,109,47,115,114,99,47,108,105,98,46,114,115],"byte_start":1,"byte_end":1584,"line_start":2,"line_end":71,"column_start":1,"column_end":2},"name":"","qualname":"::","value":"/home/tim/Rowan/Classes/ComputerArchitecture/legv8_asm/legv8_asm/src/lib.rs","parent":null,"children":[{"krate":0,"index":2},{"krate":0,"index":4},{"krate":0,"index":6},{"krate":0,"index":8},{"krate":0,"index":26},{"krate":0,"index":52},{"krate":0,"index":84},{"krate":0,"index":92},{"krate":0,"index":100},{"krate":0,"index":108},{"krate":0,"index":160},{"krate":0,"index":168},{"krate":0,"index":170}],"decl_id":null,"docs":"","sig":null,"attributes":[]},{"kind":"Mod","id":{"krate":0,"index":8},"span":{"file_name":[47,104,111,109,101,47,116,105,109,47,82,111,119,97,110,47,67,108,97,115,115,101,115,47,67,111,109,112,117,116,101,114,65,114,99,104,105,116,101,99,116,117,114,101,47,108,101,103,118,56,95,97,115,109,47,108,101,103,118,56,95,97,115,109,47,115,114,99,47,98,105,116,46,114,115],"byte_start":0,"byte_end":0,"line_start":1,"line_end":1,"column_start":1,"column_end":1},"name":"bit","qualname":"::bit","value":"/home/tim/Rowan/Classes/ComputerArchitecture/legv8_asm/legv8_asm/src/bit.rs","parent":null,"children":[{"krate":0,"index":172},{"krate":0,"index":186},{"krate":0,"index":182},{"krate":0,"index":178},{"krate":0,"index":174},{"krate":0,"index":10},{"krate":0,"index":16},{"krate":0,"index":18},{"krate":0,"index":22}],"decl_id":null,"docs":"","sig":null,"attributes":[{"value":"macro_use","span":{"file_name":[47,104,111,109,101,47,116,105,109,47,82,111,119,97,110,47,67,108,97,115,115,101,115,47,67,111,109,112,117,116,101,114,65,114,99,104,105,116,101,99,116,117,114,101,47,108,101,103,118,56,95,97,115,109,47,108,101,103,118,56,95,97,115,109,47,115,114,99,47,108,105,98,46,114,115],"byte_start":33,"byte_end":45,"line_start":5,"line_end":5,"column_start":1,"column_end":13}}]},{"kind":"TupleVariant","id":{"krate":0,"index":279},"span":{"file_name":[47,104,111,109,101,47,116,105,109,47,82,111,119,97,110,47,67,108,97,115,115,101,115,47,67,111,109,112,117,116,101,114,65,114,99,104,105,116,101,99,116,117,114,101,47,108,101,103,118,56,95,97,115,109,47,108,101,103,118,56,95,97,115,109,47,115,114,99,47,98,105,116,46,114,115],"byte_start":1664,"byte_end":1667,"line_start":5,"line_end":5,"column_start":5,"column_end":8},"name":"One","qualname":"::bit::Bit::One","value":"Bit::One","parent":{"krate":0,"index":172},"children":[],"decl_id":null,"docs":"","sig":null,"attributes":[]},{"kind":"TupleVariant","id":{"krate":0,"index":281},"span":{"file_name":[47,104,111,109,101,47,116,105,109,47,82,111,119,97,110,47,67,108,97,115,115,101,115,47,67,111,109,112,117,116,101,114,65,114,99,104,105,116,101,99,116,117,114,101,47,108,101,103,118,56,95,97,115,109,47,108,101,103,118,56,95,97,115,109,47,115,114,99,47,98,105,116,46,114,115],"byte_start":1673,"byte_end":1677,"line_start":6,"line_end":6,"column_start":5,"column_end":9},"name":"Zero","qualname":"::bit::Bit::Zero","value":"Bit::Zero","parent":{"krate":0,"index":172},"children":[],"decl_id":null,"docs":"","sig":null,"attributes":[]},{"kind":"Enum","id":{"krate":0,"index":172},"span":{"file_name":[47,104,111,109,101,47,116,105,109,47,82,111,119,97,110,47,67,108,97,115,115,101,115,47,67,111,109,112,117,116,101,114,65,114,99,104,105,116,101,99,116,117,114,101,47,108,101,103,118,56,95,97,115,109,47,108,101,103,118,56,95,97,115,109,47,115,114,99,47,98,105,116,46,114,115],"byte_start":1654,"byte_end":1657,"line_start":4,"line_end":4,"column_start":10,"column_end":13},"name":"Bit","qualname":"::bit::Bit","value":"Bit::{One, Zero}","parent":null,"children":[{"krate":0,"index":279},{"krate":0,"index":281}],"decl_id":null,"docs":" A single bit\n","sig":null,"attributes":[{"value":"rustc_copy_clone_marker","span":{"file_name":[47,104,111,109,101,47,116,105,109,47,82,111,119,97,110,47,67,108,97,115,115,101,115,47,67,111,109,112,117,116,101,114,65,114,99,104,105,116,101,99,116,117,114,101,47,108,101,103,118,56,95,97,115,109,47,108,101,103,118,56,95,97,115,109,47,115,114,99,47,98,105,116,46,114,115],"byte_start":1645,"byte_end":1680,"line_start":4,"line_end":7,"column_start":1,"column_end":2}}]},{"kind":"Method","id":{"krate":0,"index":12},"span":{"file_name":[47,104,111,109,101,47,116,105,109,47,82,111,119,97,110,47,67,108,97,115,115,101,115,47,67,111,109,112,117,116,101,114,65,114,99,104,105,116,101,99,116,117,114,101,47,108,101,103,118,56,95,97,115,109,47,108,101,103,118,56,95,97,115,109,47,115,114,99,47,98,105,116,46,114,115],"byte_start":1704,"byte_end":1711,"line_start":10,"line_end":10,"column_start":12,"column_end":19},"name":"from_u8","qualname":"<Bit>::from_u8","value":"fn (number: u8) -> Option<Bit>","parent":null,"children":[],"decl_id":null,"docs":"","sig":null,"attributes":[]},{"kind":"Method","id":{"krate":0,"index":14},"span":{"file_name":[47,104,111,109,101,47,116,105,109,47,82,111,119,97,110,47,67,108,97,115,115,101,115,47,67,111,109,112,117,116,101,114,65,114,99,104,105,116,101,99,116,117,114,101,47,108,101,103,118,56,95,97,115,109,47,108,101,103,118,56,95,97,115,109,47,115,114,99,47,98,105,116,46,114,115],"byte_start":1882,"byte_end":1891,"line_start":18,"line_end":18,"column_start":12,"column_end":21},"name":"from_bool","qualname":"<Bit>::from_bool","value":"fn (boolean: bool) -> Bit","parent":null,"children":[],"decl_id":null,"docs":"","sig":null,"attributes":[]},{"kind":"Mod","id":{"krate":0,"index":26},"span":{"file_name":[47,104,111,109,101,47,116,105,109,47,82,111,119,97,110,47,67,108,97,115,115,101,115,47,67,111,109,112,117,116,101,114,65,114,99,104,105,116,101,99,116,117,114,101,47,108,101,103,118,56,95,97,115,109,47,108,101,103,118,56,95,97,115,109,47,115,114,99,47,105,110,115,116,114,117,99,116,105,111,110,46,114,115],"byte_start":0,"byte_end":0,"line_start":1,"line_end":1,"column_start":1,"column_end":1},"name":"instruction","qualname":"::instruction","value":"/home/tim/Rowan/Classes/ComputerArchitecture/legv8_asm/legv8_asm/src/instruction.rs","parent":null,"children":[{"krate":0,"index":28},{"krate":0,"index":30},{"krate":0,"index":32},{"krate":0,"index":34},{"krate":0,"index":36},{"krate":0,"index":38},{"krate":0,"index":40},{"krate":0,"index":42},{"krate":0,"index":44},{"krate":0,"index":46},{"krate":0,"index":188},{"krate":0,"index":196},{"krate":0,"index":190},{"krate":0,"index":48}],"decl_id":null,"docs":"","sig":null,"attributes":[]},{"kind":"StructVariant","id":{"krate":0,"index":283},"span":{"file_name":[47,104,111,109,101,47,116,105,109,47,82,111,119,97,110,47,67,108,97,115,115,101,115,47,67,111,109,112,117,116,101,114,65,114,99,104,105,116,101,99,116,117,114,101,47,108,101,103,118,56,95,97,115,109,47,108,101,103,118,56,95,97,115,109,47,115,114,99,47,105,110,115,116,114,117,99,116,105,111,110,46,114,115],"byte_start":4362,"byte_end":4365,"line_start":14,"line_end":14,"column_start":5,"column_end":8},"name":"Add","qualname":"::instruction::Instruction::Add","value":"Instruction::Add { n, m, destination }","parent":{"krate":0,"index":188},"children":[],"decl_id":null,"docs":"","sig":null,"attributes":[]},{"kind":"StructVariant","id":{"krate":0,"index":291},"span":{"file_name":[47,104,111,109,101,47,116,105,109,47,82,111,119,97,110,47,67,108,97,115,115,101,115,47,67,111,109,112,117,116,101,114,65,114,99,104,105,116,101,99,116,117,114,101,47,108,101,103,118,56,95,97,115,109,47,108,101,103,118,56,95,97,115,109,47,115,114,99,47,105,110,115,116,114,117,99,116,105,111,110,46,114,115],"byte_start":4451,"byte_end":4459,"line_start":19,"line_end":19,"column_start":5,"column_end":13},"name":"Subtract","qualname":"::instruction::Instruction::Subtract","value":"Instruction::Subtract { n, m, destination }","parent":{"krate":0,"index":188},"children":[],"decl_id":null,"docs":"","sig":null,"attributes":[]},{"kind":"StructVariant","id":{"krate":0,"index":299},"span":{"file_name":[47,104,111,109,101,47,116,105,109,47,82,111,119,97,110,47,67,108,97,115,115,101,115,47,67,111,109,112,117,116,101,114,65,114,99,104,105,116,101,99,116,117,114,101,47,108,101,103,118,56,95,97,115,109,47,108,101,103,118,56,95,97,115,109,47,115,114,99,47,105,110,115,116,114,117,99,116,105,111,110,46,114,115],"byte_start":4546,"byte_end":4558,"line_start":25,"line_end":25,"column_start":5,"column_end":17},"name":"AddImmediate","qualname":"::instruction::Instruction::AddImmediate","value":"Instruction::AddImmediate { n, m, destination }","parent":{"krate":0,"index":188},"children":[],"decl_id":null,"docs":"","sig":null,"attributes":[]},{"kind":"StructVariant","id":{"krate":0,"index":307},"span":{"file_name":[47,104,111,109,101,47,116,105,109,47,82,111,119,97,110,47,67,108,97,115,115,101,115,47,67,111,109,112,117,116,101,114,65,114,99,104,105,116,101,99,116,117,114,101,47,108,101,103,118,56,95,97,115,109,47,108,101,103,118,56,95,97,115,109,47,115,114,99,47,105,110,115,116,114,117,99,116,105,111,110,46,114,115],"byte_start":4647,"byte_end":4664,"line_start":30,"line_end":30,"column_start":5,"column_end":22},"name":"SubtractImmediate","qualname":"::instruction::Instruction::SubtractImmediate","value":"Instruction::SubtractImmediate { n, m, destination }","parent":{"krate":0,"index":188},"children":[],"decl_id":null,"docs":"","sig":null,"attributes":[]},{"kind":"StructVariant","id":{"krate":0,"index":315},"span":{"file_name":[47,104,111,109,101,47,116,105,109,47,82,111,119,97,110,47,67,108,97,115,115,101,115,47,67,111,109,112,117,116,101,114,65,114,99,104,105,116,101,99,116,117,114,101,47,108,101,103,118,56,95,97,115,109,47,108,101,103,118,56,95,97,115,109,47,115,114,99,47,105,110,115,116,114,117,99,116,105,111,110,46,114,115],"byte_start":4754,"byte_end":4765,"line_start":36,"line_end":36,"column_start":5,"column_end":16},"name":"AddSetFlags","qualname":"::instruction::Instruction::AddSetFlags","value":"Instruction::AddSetFlags { n, m, destination }","parent":{"krate":0,"index":188},"children":[],"decl_id":null,"docs":"","sig":null,"attributes":[]},{"kind":"StructVariant","id":{"krate":0,"index":323},"span":{"file_name":[47,104,111,109,101,47,116,105,109,47,82,111,119,97,110,47,67,108,97,115,115,101,115,47,67,111,109,112,117,116,101,114,65,114,99,104,105,116,101,99,116,117,114,101,47,108,101,103,118,56,95,97,115,109,47,108,101,103,118,56,95,97,115,109,47,115,114,99,47,105,110,115,116,114,117,99,116,105,111,110,46,114,115],"byte_start":4851,"byte_end":4867,"line_start":41,"line_end":41,"column_start":5,"column_end":21},"name":"SubtractSetFlags","qualname":"::instruction::Instruction::SubtractSetFlags","value":"Instruction::SubtractSetFlags { n, m, destination }","parent":{"krate":0,"index":188},"children":[],"decl_id":null,"docs":"","sig":null,"attributes":[]},{"kind":"StructVariant","id":{"krate":0,"index":331},"span":{"file_name":[47,104,111,109,101,47,116,105,109,47,82,111,119,97,110,47,67,108,97,115,115,101,115,47,67,111,109,112,117,116,101,114,65,114,99,104,105,116,101,99,116,117,114,101,47,108,101,103,118,56,95,97,115,109,47,108,101,103,118,56,95,97,115,109,47,115,114,99,47,105,110,115,116,114,117,99,116,105,111,110,46,114,115],"byte_start":4954,"byte_end":4974,"line_start":47,"line_end":47,"column_start":5,"column_end":25},"name":"AddImmediateSetFlags","qualname":"::instruction::Instruction::AddImmediateSetFlags","value":"Instruction::AddImmediateSetFlags { n, m, destination }","parent":{"krate":0,"index":188},"children":[],"decl_id":null,"docs":"","sig":null,"attributes":[]},{"kind":"StructVariant","id":{"krate":0,"index":339},"span":{"file_name":[47,104,111,109,101,47,116,105,109,47,82,111,119,97,110,47,67,108,97,115,115,101,115,47,67,111,109,112,117,116,101,114,65,114,99,104,105,116,101,99,116,117,114,101,47,108,101,103,118,56,95,97,115,109,47,108,101,103,118,56,95,97,115,109,47,115,114,99,47,105,110,115,116,114,117,99,116,105,111,110,46,114,115],"byte_start":5063,"byte_end":5088,"line_start":52,"line_end":52,"column_start":5,"column_end":30},"name":"SubtractImmediateSetFlags","qualname":"::instruction::Instruction::SubtractImmediateSetFlags","value":"Instruction::SubtractImmediateSetFlags { n, m, destination }","parent":{"krate":0,"index":188},"children":[],"decl_id":null,"docs":"","sig":null,"attributes":[]},{"kind":"StructVariant","id":{"krate":0,"index":347},"span":{"file_name":[47,104,111,109,101,47,116,105,109,47,82,111,119,97,110,47,67,108,97,115,115,101,115,47,67,111,109,112,117,116,101,114,65,114,99,104,105,116,101,99,116,117,114,101,47,108,101,103,118,56,95,97,115,109,47,108,101,103,118,56,95,97,115,109,47,115,114,99,47,105,110,115,116,114,117,99,116,105,111,110,46,114,115],"byte_start":5178,"byte_end":5183,"line_start":58,"line_end":58,"column_start":5,"column_end":10},"name":"Store","qualname":"::instruction::Instruction::Store","value":"Instruction::Store { address, offset, data }","parent":{"krate":0,"index":188},"children":[],"decl_id":null,"docs":"","sig":null,"attributes":[]},{"kind":"StructVariant","id":{"krate":0,"index":355},"span":{"file_name":[47,104,111,109,101,47,116,105,109,47,82,111,119,97,110,47,67,108,97,115,115,101,115,47,67,111,109,112,117,116,101,114,65,114,99,104,105,116,101,99,116,117,114,101,47,108,101,103,118,56,95,97,115,109,47,108,101,103,118,56,95,97,115,109,47,115,114,99,47,105,110,115,116,114,117,99,116,105,111,110,46,114,115],"byte_start":5275,"byte_end":5279,"line_start":63,"line_end":63,"column_start":5,"column_end":9},"name":"Load","qualname":"::instruction::Instruction::Load","value":"Instruction::Load { address, offset, data }","parent":{"krate":0,"index":188},"children":[],"decl_id":null,"docs":"","sig":null,"attributes":[]},{"kind":"StructVariant","id":{"krate":0,"index":363},"span":{"file_name":[47,104,111,109,101,47,116,105,109,47,82,111,119,97,110,47,67,108,97,115,115,101,115,47,67,111,109,112,117,116,101,114,65,114,99,104,105,116,101,99,116,117,114,101,47,108,101,103,118,56,95,97,115,109,47,108,101,103,118,56,95,97,115,109,47,115,114,99,47,105,110,115,116,114,117,99,116,105,111,110,46,114,115],"byte_start":5372,"byte_end":5381,"line_start":69,"line_end":69,"column_start":5,"column_end":14},"name":"StoreByte","qualname":"::instruction::Instruction::StoreByte","value":"Instruction::StoreByte { address, offset, data }","parent":{"krate":0,"index":188},"children":[],"decl_id":null,"docs":"","sig":null,"attributes":[]},{"kind":"StructVariant","id":{"krate":0,"index":371},"span":{"file_name":[47,104,111,109,101,47,116,105,109,47,82,111,119,97,110,47,67,108,97,115,115,101,115,47,67,111,109,112,117,116,101,114,65,114,99,104,105,116,101,99,116,117,114,101,47,108,101,103,118,56,95,97,115,109,47,108,101,103,118,56,95,97,115,109,47,115,114,99,47,105,110,115,116,114,117,99,116,105,111,110,46,114,115],"byte_start":5473,"byte_end":5481,"line_start":74,"line_end":74,"column_start":5,"column_end":13},"name":"LoadByte","qualname":"::instruction::Instruction::LoadByte","value":"Instruction::LoadByte { address, offset, data }","parent":{"krate":0,"index":188},"children":[],"decl_id":null,"docs":"","sig":null,"attributes":[]},{"kind":"StructVariant","id":{"krate":0,"index":379},"span":{"file_name":[47,104,111,109,101,47,116,105,109,47,82,111,119,97,110,47,67,108,97,115,115,101,115,47,67,111,109,112,117,116,101,114,65,114,99,104,105,116,101,99,116,117,114,101,47,108,101,103,118,56,95,97,115,109,47,108,101,103,118,56,95,97,115,109,47,115,114,99,47,105,110,115,116,114,117,99,116,105,111,110,46,114,115],"byte_start":5574,"byte_end":5582,"line_start":80,"line_end":80,"column_start":5,"column_end":13},"name":"MoveZero","qualname":"::instruction::Instruction::MoveZero","value":"Instruction::MoveZero { immediate, shift, destination }","parent":{"krate":0,"index":188},"children":[],"decl_id":null,"docs":"","sig":null,"attributes":[]},{"kind":"StructVariant","id":{"krate":0,"index":387},"span":{"file_name":[47,104,111,109,101,47,116,105,109,47,82,111,119,97,110,47,67,108,97,115,115,101,115,47,67,111,109,112,117,116,101,114,65,114,99,104,105,116,101,99,116,117,114,101,47,108,101,103,118,56,95,97,115,109,47,108,101,103,118,56,95,97,115,109,47,115,114,99,47,105,110,115,116,114,117,99,116,105,111,110,46,114,115],"byte_start":5682,"byte_end":5690,"line_start":85,"line_end":85,"column_start":5,"column_end":13},"name":"MoveKeep","qualname":"::instruction::Instruction::MoveKeep","value":"Instruction::MoveKeep { immediate, shift, destination }","parent":{"krate":0,"index":188},"children":[],"decl_id":null,"docs":"","sig":null,"attributes":[]},{"kind":"StructVariant","id":{"krate":0,"index":395},"span":{"file_name":[47,104,111,109,101,47,116,105,109,47,82,111,119,97,110,47,67,108,97,115,115,101,115,47,67,111,109,112,117,116,101,114,65,114,99,104,105,116,101,99,116,117,114,101,47,108,101,103,118,56,95,97,115,109,47,108,101,103,118,56,95,97,115,109,47,115,114,99,47,105,110,115,116,114,117,99,116,105,111,110,46,114,115],"byte_start":5791,"byte_end":5794,"line_start":91,"line_end":91,"column_start":5,"column_end":8},"name":"And","qualname":"::instruction::Instruction::And","value":"Instruction::And { n, m, destination }","parent":{"krate":0,"index":188},"children":[],"decl_id":null,"docs":"","sig":null,"attributes":[]},{"kind":"StructVariant","id":{"krate":0,"index":403},"span":{"file_name":[47,104,111,109,101,47,116,105,109,47,82,111,119,97,110,47,67,108,97,115,115,101,115,47,67,111,109,112,117,116,101,114,65,114,99,104,105,116,101,99,116,117,114,101,47,108,101,103,118,56,95,97,115,109,47,108,101,103,118,56,95,97,115,109,47,115,114,99,47,105,110,115,116,114,117,99,116,105,111,110,46,114,115],"byte_start":5880,"byte_end":5882,"line_start":96,"line_end":96,"column_start":5,"column_end":7},"name":"Or","qualname":"::instruction::Instruction::Or","value":"Instruction::Or { n, m, destination }","parent":{"krate":0,"index":188},"children":[],"decl_id":null,"docs":"","sig":null,"attributes":[]},{"kind":"StructVariant","id":{"krate":0,"index":411},"span":{"file_name":[47,104,111,109,101,47,116,105,109,47,82,111,119,97,110,47,67,108,97,115,115,101,115,47,67,111,109,112,117,116,101,114,65,114,99,104,105,116,101,99,116,117,114,101,47,108,101,103,118,56,95,97,115,109,47,108,101,103,118,56,95,97,115,109,47,115,114,99,47,105,110,115,116,114,117,99,116,105,111,110,46,114,115],"byte_start":5968,"byte_end":5971,"line_start":101,"line_end":101,"column_start":5,"column_end":8},"name":"Xor","qualname":"::instruction::Instruction::Xor","value":"Instruction::Xor { n, m, destination }","parent":{"krate":0,"index":188},"children":[],"decl_id":null,"docs":"","sig":null,"attributes":[]},{"kind":"StructVariant","id":{"krate":0,"index":419},"span":{"file_name":[47,104,111,109,101,47,116,105,109,47,82,111,119,97,110,47,67,108,97,115,115,101,115,47,67,111,109,112,117,116,101,114,65,114,99,104,105,116,101,99,116,117,114,101,47,108,101,103,118,56,95,97,115,109,47,108,101,103,118,56,95,97,115,109,47,115,114,99,47,105,110,115,116,114,117,99,116,105,111,110,46,114,115],"byte_start":6058,"byte_end":6070,"line_start":107,"line_end":107,"column_start":5,"column_end":17},"name":"AndImmediate","qualname":"::instruction::Instruction::AndImmediate","value":"Instruction::AndImmediate { n, m, destination }","parent":{"krate":0,"index":188},"children":[],"decl_id":null,"docs":"","sig":null,"attributes":[]},{"kind":"StructVariant","id":{"krate":0,"index":427},"span":{"file_name":[47,104,111,109,101,47,116,105,109,47,82,111,119,97,110,47,67,108,97,115,115,101,115,47,67,111,109,112,117,116,101,114,65,114,99,104,105,116,101,99,116,117,114,101,47,108,101,103,118,56,95,97,115,109,47,108,101,103,118,56,95,97,115,109,47,115,114,99,47,105,110,115,116,114,117,99,116,105,111,110,46,114,115],"byte_start":6159,"byte_end":6170,"line_start":112,"line_end":112,"column_start":5,"column_end":16},"name":"OrImmediate","qualname":"::instruction::Instruction::OrImmediate","value":"Instruction::OrImmediate { n, m, destination }","parent":{"krate":0,"index":188},"children":[],"decl_id":null,"docs":"","sig":null,"attributes":[]},{"kind":"StructVariant","id":{"krate":0,"index":435},"span":{"file_name":[47,104,111,109,101,47,116,105,109,47,82,111,119,97,110,47,67,108,97,115,115,101,115,47,67,111,109,112,117,116,101,114,65,114,99,104,105,116,101,99,116,117,114,101,47,108,101,103,118,56,95,97,115,109,47,108,101,103,118,56,95,97,115,109,47,115,114,99,47,105,110,115,116,114,117,99,116,105,111,110,46,114,115],"byte_start":6259,"byte_end":6271,"line_start":117,"line_end":117,"column_start":5,"column_end":17},"name":"XorImmediate","qualname":"::instruction::Instruction::XorImmediate","value":"Instruction::XorImmediate { n, m, destination }","parent":{"krate":0,"index":188},"children":[],"decl_id":null,"docs":"","sig":null,"attributes":[]},{"kind":"StructVariant","id":{"krate":0,"index":443},"span":{"file_name":[47,104,111,109,101,47,116,105,109,47,82,111,119,97,110,47,67,108,97,115,115,101,115,47,67,111,109,112,117,116,101,114,65,114,99,104,105,116,101,99,116,117,114,101,47,108,101,103,118,56,95,97,115,109,47,108,101,103,118,56,95,97,115,109,47,115,114,99,47,105,110,115,116,114,117,99,116,105,111,110,46,114,115],"byte_start":6361,"byte_end":6372,"line_start":123,"line_end":123,"column_start":5,"column_end":16},"name":"AndSetFlags","qualname":"::instruction::Instruction::AndSetFlags","value":"Instruction::AndSetFlags { n, m, destination }","parent":{"krate":0,"index":188},"children":[],"decl_id":null,"docs":"","sig":null,"attributes":[]},{"kind":"StructVariant","id":{"krate":0,"index":451},"span":{"file_name":[47,104,111,109,101,47,116,105,109,47,82,111,119,97,110,47,67,108,97,115,115,101,115,47,67,111,109,112,117,116,101,114,65,114,99,104,105,116,101,99,116,117,114,101,47,108,101,103,118,56,95,97,115,109,47,108,101,103,118,56,95,97,115,109,47,115,114,99,47,105,110,115,116,114,117,99,116,105,111,110,46,114,115],"byte_start":6458,"byte_end":6478,"line_start":128,"line_end":128,"column_start":5,"column_end":25},"name":"AndImmediateSetFlags","qualname":"::instruction::Instruction::AndImmediateSetFlags","value":"Instruction::AndImmediateSetFlags { n, m, destination }","parent":{"krate":0,"index":188},"children":[],"decl_id":null,"docs":"","sig":null,"attributes":[]},{"kind":"StructVariant","id":{"krate":0,"index":459},"span":{"file_name":[47,104,111,109,101,47,116,105,109,47,82,111,119,97,110,47,67,108,97,115,115,101,115,47,67,111,109,112,117,116,101,114,65,114,99,104,105,116,101,99,116,117,114,101,47,108,101,103,118,56,95,97,115,109,47,108,101,103,118,56,95,97,115,109,47,115,114,99,47,105,110,115,116,114,117,99,116,105,111,110,46,114,115],"byte_start":6568,"byte_end":6585,"line_start":134,"line_end":134,"column_start":5,"column_end":22},"name":"LogicalShiftRight","qualname":"::instruction::Instruction::LogicalShiftRight","value":"Instruction::LogicalShiftRight { n, m, destination }","parent":{"krate":0,"index":188},"children":[],"decl_id":null,"docs":"","sig":null,"attributes":[]},{"kind":"StructVariant","id":{"krate":0,"index":467},"span":{"file_name":[47,104,111,109,101,47,116,105,109,47,82,111,119,97,110,47,67,108,97,115,115,101,115,47,67,111,109,112,117,116,101,114,65,114,99,104,105,116,101,99,116,117,114,101,47,108,101,103,118,56,95,97,115,109,47,108,101,103,118,56,95,97,115,109,47,115,114,99,47,105,110,115,116,114,117,99,116,105,111,110,46,114,115],"byte_start":6673,"byte_end":6689,"line_start":139,"line_end":139,"column_start":5,"column_end":21},"name":"LogicalShiftLeft","qualname":"::instruction::Instruction::LogicalShiftLeft","value":"Instruction::LogicalShiftLeft { n, m, destination }","parent":{"krate":0,"index":188},"children":[],"decl_id":null,"docs":"","sig":null,"attributes":[]},{"kind":"StructVariant","id":{"krate":0,"index":475},"span":{"file_name":[47,104,111,109,101,47,116,105,109,47,82,111,119,97,110,47,67,108,97,115,115,101,115,47,67,111,109,112,117,116,101,114,65,114,99,104,105,116,101,99,116,117,114,101,47,108,101,103,118,56,95,97,115,109,47,108,101,103,118,56,95,97,115,109,47,115,114,99,47,105,110,115,116,114,117,99,116,105,111,110,46,114,115],"byte_start":6778,"byte_end":6795,"line_start":145,"line_end":145,"column_start":5,"column_end":22},"name":"CompareBranchZero","qualname":"::instruction::Instruction::CompareBranchZero","value":"Instruction::CompareBranchZero { address, r }","parent":{"krate":0,"index":188},"children":[],"decl_id":null,"docs":"","sig":null,"attributes":[]},{"kind":"StructVariant","id":{"krate":0,"index":481},"span":{"file_name":[47,104,111,109,101,47,116,105,109,47,82,111,119,97,110,47,67,108,97,115,115,101,115,47,67,111,109,112,117,116,101,114,65,114,99,104,105,116,101,99,116,117,114,101,47,108,101,103,118,56,95,97,115,109,47,108,101,103,118,56,95,97,115,109,47,115,114,99,47,105,110,115,116,114,117,99,116,105,111,110,46,114,115],"byte_start":6859,"byte_end":6879,"line_start":149,"line_end":149,"column_start":5,"column_end":25},"name":"CompareBranchNotZero","qualname":"::instruction::Instruction::CompareBranchNotZero","value":"Instruction::CompareBranchNotZero { address, r }","parent":{"krate":0,"index":188},"children":[],"decl_id":null,"docs":"","sig":null,"attributes":[]},{"kind":"StructVariant","id":{"krate":0,"index":487},"span":{"file_name":[47,104,111,109,101,47,116,105,109,47,82,111,119,97,110,47,67,108,97,115,115,101,115,47,67,111,109,112,117,116,101,114,65,114,99,104,105,116,101,99,116,117,114,101,47,108,101,103,118,56,95,97,115,109,47,108,101,103,118,56,95,97,115,109,47,115,114,99,47,105,110,115,116,114,117,99,116,105,111,110,46,114,115],"byte_start":6944,"byte_end":6961,"line_start":154,"line_end":154,"column_start":5,"column_end":22},"name":"ConditionalBranch","qualname":"::instruction::Instruction::ConditionalBranch","value":"Instruction::ConditionalBranch { address, condition }","parent":{"krate":0,"index":188},"children":[],"decl_id":null,"docs":"","sig":null,"attributes":[]},{"kind":"StructVariant","id":{"krate":0,"index":493},"span":{"file_name":[47,104,111,109,101,47,116,105,109,47,82,111,119,97,110,47,67,108,97,115,115,101,115,47,67,111,109,112,117,116,101,114,65,114,99,104,105,116,101,99,116,117,114,101,47,108,101,103,118,56,95,97,115,109,47,108,101,103,118,56,95,97,115,109,47,115,114,99,47,105,110,115,116,114,117,99,116,105,111,110,46,114,115],"byte_start":7035,"byte_end":7041,"line_start":159,"line_end":159,"column_start":5,"column_end":11},"name":"Branch","qualname":"::instruction::Instruction::Branch","value":"Instruction::Branch { address }","parent":{"krate":0,"index":188},"children":[],"decl_id":null,"docs":"","sig":null,"attributes":[]},{"kind":"StructVariant","id":{"krate":0,"index":497},"span":{"file_name":[47,104,111,109,101,47,116,105,109,47,82,111,119,97,110,47,67,108,97,115,115,101,115,47,67,111,109,112,117,116,101,114,65,114,99,104,105,116,101,99,116,117,114,101,47,108,101,103,118,56,95,97,115,109,47,108,101,103,118,56,95,97,115,109,47,115,114,99,47,105,110,115,116,114,117,99,116,105,111,110,46,114,115],"byte_start":7084,"byte_end":7098,"line_start":162,"line_end":162,"column_start":5,"column_end":19},"name":"BranchRegister","qualname":"::instruction::Instruction::BranchRegister","value":"Instruction::BranchRegister { r }","parent":{"krate":0,"index":188},"children":[],"decl_id":null,"docs":"","sig":null,"attributes":[]},{"kind":"StructVariant","id":{"krate":0,"index":501},"span":{"file_name":[47,104,111,109,101,47,116,105,109,47,82,111,119,97,110,47,67,108,97,115,115,101,115,47,67,111,109,112,117,116,101,114,65,114,99,104,105,116,101,99,116,117,114,101,47,108,101,103,118,56,95,97,115,109,47,108,101,103,118,56,95,97,115,109,47,115,114,99,47,105,110,115,116,114,117,99,116,105,111,110,46,114,115],"byte_start":7132,"byte_end":7142,"line_start":165,"line_end":165,"column_start":5,"column_end":15},"name":"BranchLink","qualname":"::instruction::Instruction::BranchLink","value":"Instruction::BranchLink { address }","parent":{"krate":0,"index":188},"children":[],"decl_id":null,"docs":"","sig":null,"attributes":[]},{"kind":"Enum","id":{"krate":0,"index":188},"span":{"file_name":[47,104,111,109,101,47,116,105,109,47,82,111,119,97,110,47,67,108,97,115,115,101,115,47,67,111,109,112,117,116,101,114,65,114,99,104,105,116,101,99,116,117,114,101,47,108,101,103,118,56,95,97,115,109,47,108,101,103,118,56,95,97,115,109,47,115,114,99,47,105,110,115,116,114,117,99,116,105,111,110,46,114,115],"byte_start":4344,"byte_end":4355,"line_start":13,"line_end":13,"column_start":10,"column_end":21},"name":"Instruction","qualname":"::instruction::Instruction","value":"Instruction::{Add, Subtract, AddImmediate, SubtractImmediate, AddSetFlags, SubtractSetFlags, AddImmediateSetFlags, SubtractImmediateSetFlags, Store, Load, StoreByte, LoadByte, MoveZero, MoveKeep, And, Or, Xor, AndImmediate, OrImmediate, XorImmediate, AndSetFlags, AndImmediateSetFlags, LogicalShiftRight, LogicalShiftLeft, CompareBranchZero, CompareBranchNotZero, ConditionalBranch, Branch, BranchRegister, BranchLink}","parent":null,"children":[{"krate":0,"index":283},{"krate":0,"index":291},{"krate":0,"index":299},{"krate":0,"index":307},{"krate":0,"index":315},{"krate":0,"index":323},{"krate":0,"index":331},{"krate":0,"index":339},{"krate":0,"index":347},{"krate":0,"index":355},{"krate":0,"index":363},{"krate":0,"index":371},{"krate":0,"index":379},{"krate":0,"index":387},{"krate":0,"index":395},{"krate":0,"index":403},{"krate":0,"index":411},{"krate":0,"index":419},{"krate":0,"index":427},{"krate":0,"index":435},{"krate":0,"index":443},{"krate":0,"index":451},{"krate":0,"index":459},{"krate":0,"index":467},{"krate":0,"index":475},{"krate":0,"index":481},{"krate":0,"index":487},{"krate":0,"index":493},{"krate":0,"index":497},{"krate":0,"index":501}],"decl_id":null,"docs":"","sig":null,"attributes":[]},{"kind":"Mod","id":{"krate":0,"index":52},"span":{"file_name":[47,104,111,109,101,47,116,105,109,47,82,111,119,97,110,47,67,108,97,115,115,101,115,47,67,111,109,112,117,116,101,114,65,114,99,104,105,116,101,99,116,117,114,101,47,108,101,103,118,56,95,97,115,109,47,108,101,103,118,56,95,97,115,109,47,115,114,99,47,112,97,114,115,101,114,46,114,115],"byte_start":0,"byte_end":0,"line_start":1,"line_end":1,"column_start":1,"column_end":1},"name":"parser","qualname":"::parser","value":"/home/tim/Rowan/Classes/ComputerArchitecture/legv8_asm/legv8_asm/src/parser.rs","parent":null,"children":[{"krate":0,"index":54},{"krate":0,"index":56},{"krate":0,"index":58},{"krate":0,"index":60},{"krate":0,"index":62},{"krate":0,"index":64},{"krate":0,"index":66},{"krate":0,"index":68},{"krate":0,"index":70},{"krate":0,"index":72},{"krate":0,"index":74},{"krate":0,"index":76},{"krate":0,"index":78},{"krate":0,"index":80},{"krate":0,"index":200},{"krate":0,"index":204},{"krate":0,"index":208},{"krate":0,"index":212},{"krate":0,"index":216},{"krate":0,"index":220},{"krate":0,"index":224},{"krate":0,"index":228},{"krate":0,"index":232},{"krate":0,"index":236},{"krate":0,"index":82}],"decl_id":null,"docs":"","sig":null,"attributes":[{"value":"allow(unused_imports)","span":{"file_name":[47,104,111,109,101,47,116,105,109,47,82,111,119,97,110,47,67,108,97,115,115,101,115,47,67,111,109,112,117,116,101,114,65,114,99,104,105,116,101,99,116,117,114,101,47,108,101,103,118,56,95,97,115,109,47,108,101,103,118,56,95,97,115,109,47,115,114,99,47,112,97,114,115,101,114,46,114,115],"byte_start":30789,"byte_end":30814,"line_start":1,"line_end":1,"column_start":1,"column_end":26}}]},{"kind":"Function","id":{"krate":0,"index":82},"span":{"file_name":[47,104,111,109,101,47,116,105,109,47,82,111,119,97,110,47,67,108,97,115,115,101,115,47,67,111,109,112,117,116,101,114,65,114,99,104,105,116,101,99,116,117,114,101,47,108,101,103,118,56,95,97,115,109,47,108,101,103,118,56,95,97,115,109,47,115,114,99,47,112,97,114,115,101,114,46,114,115],"byte_start":44815,"byte_end":44826,"line_start":341,"line_end":341,"column_start":8,"column_end":19},"name":"parse_lines","qualname":"::parser::parse_lines","value":"fn (lines: &str) -> Vec<IResult<CompleteStr, Instruction>>","parent":null,"children":[],"decl_id":null,"docs":" Parse lines to instructions\n","sig":null,"attributes":[]},{"kind":"Mod","id":{"krate":0,"index":84},"span":{"file_name":[47,104,111,109,101,47,116,105,109,47,82,111,119,97,110,47,67,108,97,115,115,101,115,47,67,111,109,112,117,116,101,114,65,114,99,104,105,116,101,99,116,117,114,101,47,108,101,103,118,56,95,97,115,109,47,108,101,103,118,56,95,97,115,109,47,115,114,99,47,114,101,103,105,115,116,101,114,46,114,115],"byte_start":0,"byte_end":0,"line_start":1,"line_end":1,"column_start":1,"column_end":1},"name":"register","qualname":"::register","value":"/home/tim/Rowan/Classes/ComputerArchitecture/legv8_asm/legv8_asm/src/register.rs","parent":null,"children":[{"krate":0,"index":86},{"krate":0,"index":240},{"krate":0,"index":254},{"krate":0,"index":250},{"krate":0,"index":246},{"krate":0,"index":242},{"krate":0,"index":88}],"decl_id":null,"docs":"","sig":null,"attributes":[]},{"kind":"TupleVariant","id":{"krate":0,"index":505},"span":{"file_name":[47,104,111,109,101,47,116,105,109,47,82,111,119,97,110,47,67,108,97,115,115,101,115,47,67,111,109,112,117,116,101,114,65,114,99,104,105,116,101,99,116,117,114,101,47,108,101,103,118,56,95,97,115,109,47,108,101,103,118,56,95,97,115,109,47,115,114,99,47,114,101,103,105,115,116,101,114,46,114,115],"byte_start":64521,"byte_end":64523,"line_start":5,"line_end":5,"column_start":5,"column_end":7},"name":"X0","qualname":"::register::Register::X0","value":"Register::X0","parent":{"krate":0,"index":240},"children":[],"decl_id":null,"docs":"","sig":null,"attributes":[]},{"kind":"TupleVariant","id":{"krate":0,"index":509},"span":{"file_name":[47,104,111,109,101,47,116,105,109,47,82,111,119,97,110,47,67,108,97,115,115,101,115,47,67,111,109,112,117,116,101,114,65,114,99,104,105,116,101,99,116,117,114,101,47,108,101,103,118,56,95,97,115,109,47,108,101,103,118,56,95,97,115,109,47,115,114,99,47,114,101,103,105,115,116,101,114,46,114,115],"byte_start":64533,"byte_end":64535,"line_start":6,"line_end":6,"column_start":5,"column_end":7},"name":"X1","qualname":"::register::Register::X1","value":"Register::X1","parent":{"krate":0,"index":240},"children":[],"decl_id":null,"docs":"","sig":null,"attributes":[]},{"kind":"TupleVariant","id":{"krate":0,"index":511},"span":{"file_name":[47,104,111,109,101,47,116,105,109,47,82,111,119,97,110,47,67,108,97,115,115,101,115,47,67,111,109,112,117,116,101,114,65,114,99,104,105,116,101,99,116,117,114,101,47,108,101,103,118,56,95,97,115,109,47,108,101,103,118,56,95,97,115,109,47,115,114,99,47,114,101,103,105,115,116,101,114,46,114,115],"byte_start":64541,"byte_end":64543,"line_start":7,"line_end":7,"column_start":5,"column_end":7},"name":"X2","qualname":"::register::Register::X2","value":"Register::X2","parent":{"krate":0,"index":240},"children":[],"decl_id":null,"docs":"","sig":null,"attributes":[]},{"kind":"TupleVariant","id":{"krate":0,"index":513},"span":{"file_name":[47,104,111,109,101,47,116,105,109,47,82,111,119,97,110,47,67,108,97,115,115,101,115,47,67,111,109,112,117,116,101,114,65,114,99,104,105,116,101,99,116,117,114,101,47,108,101,103,118,56,95,97,115,109,47,108,101,103,118,56,95,97,115,109,47,115,114,99,47,114,101,103,105,115,116,101,114,46,114,115],"byte_start":64549,"byte_end":64551,"line_start":8,"line_end":8,"column_start":5,"column_end":7},"name":"X3","qualname":"::register::Register::X3","value":"Register::X3","parent":{"krate":0,"index":240},"children":[],"decl_id":null,"docs":"","sig":null,"attributes":[]},{"kind":"TupleVariant","id":{"krate":0,"index":515},"span":{"file_name":[47,104,111,109,101,47,116,105,109,47,82,111,119,97,110,47,67,108,97,115,115,101,115,47,67,111,109,112,117,116,101,114,65,114,99,104,105,116,101,99,116,117,114,101,47,108,101,103,118,56,95,97,115,109,47,108,101,103,118,56,95,97,115,109,47,115,114,99,47,114,101,103,105,115,116,101,114,46,114,115],"byte_start":64557,"byte_end":64559,"line_start":9,"line_end":9,"column_start":5,"column_end":7},"name":"X4","qualname":"::register::Register::X4","value":"Register::X4","parent":{"krate":0,"index":240},"children":[],"decl_id":null,"docs":"","sig":null,"attributes":[]},{"kind":"TupleVariant","id":{"krate":0,"index":517},"span":{"file_name":[47,104,111,109,101,47,116,105,109,47,82,111,119,97,110,47,67,108,97,115,115,101,115,47,67,111,109,112,117,116,101,114,65,114,99,104,105,116,101,99,116,117,114,101,47,108,101,103,118,56,95,97,115,109,47,108,101,103,118,56,95,97,115,109,47,115,114,99,47,114,101,103,105,115,116,101,114,46,114,115],"byte_start":64565,"byte_end":64567,"line_start":10,"line_end":10,"column_start":5,"column_end":7},"name":"X5","qualname":"::register::Register::X5","value":"Register::X5","parent":{"krate":0,"index":240},"children":[],"decl_id":null,"docs":"","sig":null,"attributes":[]},{"kind":"TupleVariant","id":{"krate":0,"index":519},"span":{"file_name":[47,104,111,109,101,47,116,105,109,47,82,111,119,97,110,47,67,108,97,115,115,101,115,47,67,111,109,112,117,116,101,114,65,114,99,104,105,116,101,99,116,117,114,101,47,108,101,103,118,56,95,97,115,109,47,108,101,103,118,56,95,97,115,109,47,115,114,99,47,114,101,103,105,115,116,101,114,46,114,115],"byte_start":64573,"byte_end":64575,"line_start":11,"line_end":11,"column_start":5,"column_end":7},"name":"X6","qualname":"::register::Register::X6","value":"Register::X6","parent":{"krate":0,"index":240},"children":[],"decl_id":null,"docs":"","sig":null,"attributes":[]},{"kind":"TupleVariant","id":{"krate":0,"index":521},"span":{"file_name":[47,104,111,109,101,47,116,105,109,47,82,111,119,97,110,47,67,108,97,115,115,101,115,47,67,111,109,112,117,116,101,114,65,114,99,104,105,116,101,99,116,117,114,101,47,108,101,103,118,56,95,97,115,109,47,108,101,103,118,56,95,97,115,109,47,115,114,99,47,114,101,103,105,115,116,101,114,46,114,115],"byte_start":64581,"byte_end":64583,"line_start":12,"line_end":12,"column_start":5,"column_end":7},"name":"X7","qualname":"::register::Register::X7","value":"Register::X7","parent":{"krate":0,"index":240},"children":[],"decl_id":null,"docs":"","sig":null,"attributes":[]},{"kind":"TupleVariant","id":{"krate":0,"index":523},"span":{"file_name":[47,104,111,109,101,47,116,105,109,47,82,111,119,97,110,47,67,108,97,115,115,101,115,47,67,111,109,112,117,116,101,114,65,114,99,104,105,116,101,99,116,117,114,101,47,108,101,103,118,56,95,97,115,109,47,108,101,103,118,56,95,97,115,109,47,115,114,99,47,114,101,103,105,115,116,101,114,46,114,115],"byte_start":64589,"byte_end":64591,"line_start":13,"line_end":13,"column_start":5,"column_end":7},"name":"X8","qualname":"::register::Register::X8","value":"Register::X8","parent":{"krate":0,"index":240},"children":[],"decl_id":null,"docs":"","sig":null,"attributes":[]},{"kind":"TupleVariant","id":{"krate":0,"index":525},"span":{"file_name":[47,104,111,109,101,47,116,105,109,47,82,111,119,97,110,47,67,108,97,115,115,101,115,47,67,111,109,112,117,116,101,114,65,114,99,104,105,116,101,99,116,117,114,101,47,108,101,103,118,56,95,97,115,109,47,108,101,103,118,56,95,97,115,109,47,115,114,99,47,114,101,103,105,115,116,101,114,46,114,115],"byte_start":64597,"byte_end":64599,"line_start":14,"line_end":14,"column_start":5,"column_end":7},"name":"X9","qualname":"::register::Register::X9","value":"Register::X9","parent":{"krate":0,"index":240},"children":[],"decl_id":null,"docs":"","sig":null,"attributes":[]},{"kind":"TupleVariant","id":{"krate":0,"index":527},"span":{"file_name":[47,104,111,109,101,47,116,105,109,47,82,111,119,97,110,47,67,108,97,115,115,101,115,47,67,111,109,112,117,116,101,114,65,114,99,104,105,116,101,99,116,117,114,101,47,108,101,103,118,56,95,97,115,109,47,108,101,103,118,56,95,97,115,109,47,115,114,99,47,114,101,103,105,115,116,101,114,46,114,115],"byte_start":64605,"byte_end":64608,"line_start":15,"line_end":15,"column_start":5,"column_end":8},"name":"X10","qualname":"::register::Register::X10","value":"Register::X10","parent":{"krate":0,"index":240},"children":[],"decl_id":null,"docs":"","sig":null,"attributes":[]},{"kind":"TupleVariant","id":{"krate":0,"index":529},"span":{"file_name":[47,104,111,109,101,47,116,105,109,47,82,111,119,97,110,47,67,108,97,115,115,101,115,47,67,111,109,112,117,116,101,114,65,114,99,104,105,116,101,99,116,117,114,101,47,108,101,103,118,56,95,97,115,109,47,108,101,103,118,56,95,97,115,109,47,115,114,99,47,114,101,103,105,115,116,101,114,46,114,115],"byte_start":64614,"byte_end":64617,"line_start":16,"line_end":16,"column_start":5,"column_end":8},"name":"X11","qualname":"::register::Register::X11","value":"Register::X11","parent":{"krate":0,"index":240},"children":[],"decl_id":null,"docs":"","sig":null,"attributes":[]},{"kind":"TupleVariant","id":{"krate":0,"index":531},"span":{"file_name":[47,104,111,109,101,47,116,105,109,47,82,111,119,97,110,47,67,108,97,115,115,101,115,47,67,111,109,112,117,116,101,114,65,114,99,104,105,116,101,99,116,117,114,101,47,108,101,103,118,56,95,97,115,109,47,108,101,103,118,56,95,97,115,109,47,115,114,99,47,114,101,103,105,115,116,101,114,46,114,115],"byte_start":64623,"byte_end":64626,"line_start":17,"line_end":17,"column_start":5,"column_end":8},"name":"X12","qualname":"::register::Register::X12","value":"Register::X12","parent":{"krate":0,"index":240},"children":[],"decl_id":null,"docs":"","sig":null,"attributes":[]},{"kind":"TupleVariant","id":{"krate":0,"index":533},"span":{"file_name":[47,104,111,109,101,47,116,105,109,47,82,111,119,97,110,47,67,108,97,115,115,101,115,47,67,111,109,112,117,116,101,114,65,114,99,104,105,116,101,99,116,117,114,101,47,108,101,103,118,56,95,97,115,109,47,108,101,103,118,56,95,97,115,109,47,115,114,99,47,114,101,103,105,115,116,101,114,46,114,115],"byte_start":64632,"byte_end":64635,"line_start":18,"line_end":18,"column_start":5,"column_end":8},"name":"X13","qualname":"::register::Register::X13","value":"Register::X13","parent":{"krate":0,"index":240},"children":[],"decl_id":null,"docs":"","sig":null,"attributes":[]},{"kind":"TupleVariant","id":{"krate":0,"index":535},"span":{"file_name":[47,104,111,109,101,47,116,105,109,47,82,111,119,97,110,47,67,108,97,115,115,101,115,47,67,111,109,112,117,116,101,114,65,114,99,104,105,116,101,99,116,117,114,101,47,108,101,103,118,56,95,97,115,109,47,108,101,103,118,56,95,97,115,109,47,115,114,99,47,114,101,103,105,115,116,101,114,46,114,115],"byte_start":64641,"byte_end":64644,"line_start":19,"line_end":19,"column_start":5,"column_end":8},"name":"X14","qualname":"::register::Register::X14","value":"Register::X14","parent":{"krate":0,"index":240},"children":[],"decl_id":null,"docs":"","sig":null,"attributes":[]},{"kind":"TupleVariant","id":{"krate":0,"index":537},"span":{"file_name":[47,104,111,109,101,47,116,105,109,47,82,111,119,97,110,47,67,108,97,115,115,101,115,47,67,111,109,112,117,116,101,114,65,114,99,104,105,116,101,99,116,117,114,101,47,108,101,103,118,56,95,97,115,109,47,108,101,103,118,56,95,97,115,109,47,115,114,99,47,114,101,103,105,115,116,101,114,46,114,115],"byte_start":64650,"byte_end":64653,"line_start":20,"line_end":20,"column_start":5,"column_end":8},"name":"X15","qualname":"::register::Register::X15","value":"Register::X15","parent":{"krate":0,"index":240},"children":[],"decl_id":null,"docs":"","sig":null,"attributes":[]},{"kind":"TupleVariant","id":{"krate":0,"index":539},"span":{"file_name":[47,104,111,109,101,47,116,105,109,47,82,111,119,97,110,47,67,108,97,115,115,101,115,47,67,111,109,112,117,116,101,114,65,114,99,104,105,116,101,99,116,117,114,101,47,108,101,103,118,56,95,97,115,109,47,108,101,103,118,56,95,97,115,109,47,115,114,99,47,114,101,103,105,115,116,101,114,46,114,115],"byte_start":64659,"byte_end":64662,"line_start":21,"line_end":21,"column_start":5,"column_end":8},"name":"X16","qualname":"::register::Register::X16","value":"Register::X16","parent":{"krate":0,"index":240},"children":[],"decl_id":null,"docs":"","sig":null,"attributes":[]},{"kind":"TupleVariant","id":{"krate":0,"index":541},"span":{"file_name":[47,104,111,109,101,47,116,105,109,47,82,111,119,97,110,47,67,108,97,115,115,101,115,47,67,111,109,112,117,116,101,114,65,114,99,104,105,116,101,99,116,117,114,101,47,108,101,103,118,56,95,97,115,109,47,108,101,103,118,56,95,97,115,109,47,115,114,99,47,114,101,103,105,115,116,101,114,46,114,115],"byte_start":64668,"byte_end":64671,"line_start":22,"line_end":22,"column_start":5,"column_end":8},"name":"X17","qualname":"::register::Register::X17","value":"Register::X17","parent":{"krate":0,"index":240},"children":[],"decl_id":null,"docs":"","sig":null,"attributes":[]},{"kind":"TupleVariant","id":{"krate":0,"index":543},"span":{"file_name":[47,104,111,109,101,47,116,105,109,47,82,111,119,97,110,47,67,108,97,115,115,101,115,47,67,111,109,112,117,116,101,114,65,114,99,104,105,116,101,99,116,117,114,101,47,108,101,103,118,56,95,97,115,109,47,108,101,103,118,56,95,97,115,109,47,115,114,99,47,114,101,103,105,115,116,101,114,46,114,115],"byte_start":64677,"byte_end":64680,"line_start":23,"line_end":23,"column_start":5,"column_end":8},"name":"X18","qualname":"::register::Register::X18","value":"Register::X18","parent":{"krate":0,"index":240},"children":[],"decl_id":null,"docs":"","sig":null,"attributes":[]},{"kind":"TupleVariant","id":{"krate":0,"index":545},"span":{"file_name":[47,104,111,109,101,47,116,105,109,47,82,111,119,97,110,47,67,108,97,115,115,101,115,47,67,111,109,112,117,116,101,114,65,114,99,104,105,116,101,99,116,117,114,101,47,108,101,103,118,56,95,97,115,109,47,108,101,103,118,56,95,97,115,109,47,115,114,99,47,114,101,103,105,115,116,101,114,46,114,115],"byte_start":64686,"byte_end":64689,"line_start":24,"line_end":24,"column_start":5,"column_end":8},"name":"X19","qualname":"::register::Register::X19","value":"Register::X19","parent":{"krate":0,"index":240},"children":[],"decl_id":null,"docs":"","sig":null,"attributes":[]},{"kind":"TupleVariant","id":{"krate":0,"index":547},"span":{"file_name":[47,104,111,109,101,47,116,105,109,47,82,111,119,97,110,47,67,108,97,115,115,101,115,47,67,111,109,112,117,116,101,114,65,114,99,104,105,116,101,99,116,117,114,101,47,108,101,103,118,56,95,97,115,109,47,108,101,103,118,56,95,97,115,109,47,115,114,99,47,114,101,103,105,115,116,101,114,46,114,115],"byte_start":64695,"byte_end":64698,"line_start":25,"line_end":25,"column_start":5,"column_end":8},"name":"X20","qualname":"::register::Register::X20","value":"Register::X20","parent":{"krate":0,"index":240},"children":[],"decl_id":null,"docs":"","sig":null,"attributes":[]},{"kind":"TupleVariant","id":{"krate":0,"index":549},"span":{"file_name":[47,104,111,109,101,47,116,105,109,47,82,111,119,97,110,47,67,108,97,115,115,101,115,47,67,111,109,112,117,116,101,114,65,114,99,104,105,116,101,99,116,117,114,101,47,108,101,103,118,56,95,97,115,109,47,108,101,103,118,56,95,97,115,109,47,115,114,99,47,114,101,103,105,115,116,101,114,46,114,115],"byte_start":64704,"byte_end":64707,"line_start":26,"line_end":26,"column_start":5,"column_end":8},"name":"X21","qualname":"::register::Register::X21","value":"Register::X21","parent":{"krate":0,"index":240},"children":[],"decl_id":null,"docs":"","sig":null,"attributes":[]},{"kind":"TupleVariant","id":{"krate":0,"index":551},"span":{"file_name":[47,104,111,109,101,47,116,105,109,47,82,111,119,97,110,47,67,108,97,115,115,101,115,47,67,111,109,112,117,116,101,114,65,114,99,104,105,116,101,99,116,117,114,101,47,108,101,103,118,56,95,97,115,109,47,108,101,103,118,56,95,97,115,109,47,115,114,99,47,114,101,103,105,115,116,101,114,46,114,115],"byte_start":64713,"byte_end":64716,"line_start":27,"line_end":27,"column_start":5,"column_end":8},"name":"X22","qualname":"::register::Register::X22","value":"Register::X22","parent":{"krate":0,"index":240},"children":[],"decl_id":null,"docs":"","sig":null,"attributes":[]},{"kind":"TupleVariant","id":{"krate":0,"index":553},"span":{"file_name":[47,104,111,109,101,47,116,105,109,47,82,111,119,97,110,47,67,108,97,115,115,101,115,47,67,111,109,112,117,116,101,114,65,114,99,104,105,116,101,99,116,117,114,101,47,108,101,103,118,56,95,97,115,109,47,108,101,103,118,56,95,97,115,109,47,115,114,99,47,114,101,103,105,115,116,101,114,46,114,115],"byte_start":64722,"byte_end":64725,"line_start":28,"line_end":28,"column_start":5,"column_end":8},"name":"X23","qualname":"::register::Register::X23","value":"Register::X23","parent":{"krate":0,"index":240},"children":[],"decl_id":null,"docs":"","sig":null,"attributes":[]},{"kind":"TupleVariant","id":{"krate":0,"index":555},"span":{"file_name":[47,104,111,109,101,47,116,105,109,47,82,111,119,97,110,47,67,108,97,115,115,101,115,47,67,111,109,112,117,116,101,114,65,114,99,104,105,116,101,99,116,117,114,101,47,108,101,103,118,56,95,97,115,109,47,108,101,103,118,56,95,97,115,109,47,115,114,99,47,114,101,103,105,115,116,101,114,46,114,115],"byte_start":64731,"byte_end":64734,"line_start":29,"line_end":29,"column_start":5,"column_end":8},"name":"X24","qualname":"::register::Register::X24","value":"Register::X24","parent":{"krate":0,"index":240},"children":[],"decl_id":null,"docs":"","sig":null,"attributes":[]},{"kind":"TupleVariant","id":{"krate":0,"index":557},"span":{"file_name":[47,104,111,109,101,47,116,105,109,47,82,111,119,97,110,47,67,108,97,115,115,101,115,47,67,111,109,112,117,116,101,114,65,114,99,104,105,116,101,99,116,117,114,101,47,108,101,103,118,56,95,97,115,109,47,108,101,103,118,56,95,97,115,109,47,115,114,99,47,114,101,103,105,115,116,101,114,46,114,115],"byte_start":64740,"byte_end":64743,"line_start":30,"line_end":30,"column_start":5,"column_end":8},"name":"X25","qualname":"::register::Register::X25","value":"Register::X25","parent":{"krate":0,"index":240},"children":[],"decl_id":null,"docs":"","sig":null,"attributes":[]},{"kind":"TupleVariant","id":{"krate":0,"index":559},"span":{"file_name":[47,104,111,109,101,47,116,105,109,47,82,111,119,97,110,47,67,108,97,115,115,101,115,47,67,111,109,112,117,116,101,114,65,114,99,104,105,116,101,99,116,117,114,101,47,108,101,103,118,56,95,97,115,109,47,108,101,103,118,56,95,97,115,109,47,115,114,99,47,114,101,103,105,115,116,101,114,46,114,115],"byte_start":64749,"byte_end":64752,"line_start":31,"line_end":31,"column_start":5,"column_end":8},"name":"X26","qualname":"::register::Register::X26","value":"Register::X26","parent":{"krate":0,"index":240},"children":[],"decl_id":null,"docs":"","sig":null,"attributes":[]},{"kind":"TupleVariant","id":{"krate":0,"index":561},"span":{"file_name":[47,104,111,109,101,47,116,105,109,47,82,111,119,97,110,47,67,108,97,115,115,101,115,47,67,111,109,112,117,116,101,114,65,114,99,104,105,116,101,99,116,117,114,101,47,108,101,103,118,56,95,97,115,109,47,108,101,103,118,56,95,97,115,109,47,115,114,99,47,114,101,103,105,115,116,101,114,46,114,115],"byte_start":64758,"byte_end":64761,"line_start":32,"line_end":32,"column_start":5,"column_end":8},"name":"X27","qualname":"::register::Register::X27","value":"Register::X27","parent":{"krate":0,"index":240},"children":[],"decl_id":null,"docs":"","sig":null,"attributes":[]},{"kind":"TupleVariant","id":{"krate":0,"index":563},"span":{"file_name":[47,104,111,109,101,47,116,105,109,47,82,111,119,97,110,47,67,108,97,115,115,101,115,47,67,111,109,112,117,116,101,114,65,114,99,104,105,116,101,99,116,117,114,101,47,108,101,103,118,56,95,97,115,109,47,108,101,103,118,56,95,97,115,109,47,115,114,99,47,114,101,103,105,115,116,101,114,46,114,115],"byte_start":64767,"byte_end":64770,"line_start":33,"line_end":33,"column_start":5,"column_end":8},"name":"X28","qualname":"::register::Register::X28","value":"Register::X28","parent":{"krate":0,"index":240},"children":[],"decl_id":null,"docs":"","sig":null,"attributes":[]},{"kind":"TupleVariant","id":{"krate":0,"index":565},"span":{"file_name":[47,104,111,109,101,47,116,105,109,47,82,111,119,97,110,47,67,108,97,115,115,101,115,47,67,111,109,112,117,116,101,114,65,114,99,104,105,116,101,99,116,117,114,101,47,108,101,103,118,56,95,97,115,109,47,108,101,103,118,56,95,97,115,109,47,115,114,99,47,114,101,103,105,115,116,101,114,46,114,115],"byte_start":64776,"byte_end":64779,"line_start":34,"line_end":34,"column_start":5,"column_end":8},"name":"X29","qualname":"::register::Register::X29","value":"Register::X29","parent":{"krate":0,"index":240},"children":[],"decl_id":null,"docs":"","sig":null,"attributes":[]},{"kind":"TupleVariant","id":{"krate":0,"index":567},"span":{"file_name":[47,104,111,109,101,47,116,105,109,47,82,111,119,97,110,47,67,108,97,115,115,101,115,47,67,111,109,112,117,116,101,114,65,114,99,104,105,116,101,99,116,117,114,101,47,108,101,103,118,56,95,97,115,109,47,108,101,103,118,56,95,97,115,109,47,115,114,99,47,114,101,103,105,115,116,101,114,46,114,115],"byte_start":64785,"byte_end":64788,"line_start":35,"line_end":35,"column_start":5,"column_end":8},"name":"X30","qualname":"::register::Register::X30","value":"Register::X30","parent":{"krate":0,"index":240},"children":[],"decl_id":null,"docs":"","sig":null,"attributes":[]},{"kind":"TupleVariant","id":{"krate":0,"index":569},"span":{"file_name":[47,104,111,109,101,47,116,105,109,47,82,111,119,97,110,47,67,108,97,115,115,101,115,47,67,111,109,112,117,116,101,114,65,114,99,104,105,116,101,99,116,117,114,101,47,108,101,103,118,56,95,97,115,109,47,108,101,103,118,56,95,97,115,109,47,115,114,99,47,114,101,103,105,115,116,101,114,46,114,115],"byte_start":64794,"byte_end":64797,"line_start":36,"line_end":36,"column_start":5,"column_end":8},"name":"XZR","qualname":"::register::Register::XZR","value":"Register::XZR","parent":{"krate":0,"index":240},"children":[],"decl_id":null,"docs":"","sig":null,"attributes":[]},{"kind":"Enum","id":{"krate":0,"index":240},"span":{"file_name":[47,104,111,109,101,47,116,105,109,47,82,111,119,97,110,47,67,108,97,115,115,101,115,47,67,111,109,112,117,116,101,114,65,114,99,104,105,116,101,99,116,117,114,101,47,108,101,103,118,56,95,97,115,109,47,108,101,103,118,56,95,97,115,109,47,115,114,99,47,114,101,103,105,115,116,101,114,46,114,115],"byte_start":64506,"byte_end":64514,"line_start":4,"line_end":4,"column_start":10,"column_end":18},"name":"Register","qualname":"::register::Register","value":"Register::{X0, X1, X2, X3, X4, X5, X6, X7, X8, X9, X10, X11, X12, X13, X14, X15, X16, X17, X18, X19, X20, X21, X22, X23, X24, X25, X26, X27, X28, X29, X30, XZR}","parent":null,"children":[{"krate":0,"index":505},{"krate":0,"index":509},{"krate":0,"index":511},{"krate":0,"index":513},{"krate":0,"index":515},{"krate":0,"index":517},{"krate":0,"index":519},{"krate":0,"index":521},{"krate":0,"index":523},{"krate":0,"index":525},{"krate":0,"index":527},{"krate":0,"index":529},{"krate":0,"index":531},{"krate":0,"index":533},{"krate":0,"index":535},{"krate":0,"index":537},{"krate":0,"index":539},{"krate":0,"index":541},{"krate":0,"index":543},{"krate":0,"index":545},{"krate":0,"index":547},{"krate":0,"index":549},{"krate":0,"index":551},{"krate":0,"index":553},{"krate":0,"index":555},{"krate":0,"index":557},{"krate":0,"index":559},{"krate":0,"index":561},{"krate":0,"index":563},{"krate":0,"index":565},{"krate":0,"index":567},{"krate":0,"index":569}],"decl_id":null,"docs":"","sig":null,"attributes":[{"value":"rustc_copy_clone_marker","span":{"file_name":[47,104,111,109,101,47,116,105,109,47,82,111,119,97,110,47,67,108,97,115,115,101,115,47,67,111,109,112,117,116,101,114,65,114,99,104,105,116,101,99,116,117,114,101,47,108,101,103,118,56,95,97,115,109,47,108,101,103,118,56,95,97,115,109,47,115,114,99,47,114,101,103,105,115,116,101,114,46,114,115],"byte_start":64497,"byte_end":64800,"line_start":4,"line_end":37,"column_start":1,"column_end":2}}]},{"kind":"Mod","id":{"krate":0,"index":92},"span":{"file_name":[47,104,111,109,101,47,116,105,109,47,82,111,119,97,110,47,67,108,97,115,115,101,115,47,67,111,109,112,117,116,101,114,65,114,99,104,105,116,101,99,116,117,114,101,47,108,101,103,118,56,95,97,115,109,47,108,101,103,118,56,95,97,115,109,47,115,114,99,47,115,104,105,102,116,49,54,46,114,115],"byte_start":0,"byte_end":0,"line_start":1,"line_end":1,"column_start":1,"column_end":1},"name":"shift16","qualname":"::shift16","value":"/home/tim/Rowan/Classes/ComputerArchitecture/legv8_asm/legv8_asm/src/shift16.rs","parent":null,"children":[{"krate":0,"index":94},{"krate":0,"index":256},{"krate":0,"index":262},{"krate":0,"index":258},{"krate":0,"index":96}],"decl_id":null,"docs":"","sig":null,"attributes":[]},{"kind":"TupleVariant","id":{"krate":0,"index":571},"span":{"file_name":[47,104,111,109,101,47,116,105,109,47,82,111,119,97,110,47,67,108,97,115,115,101,115,47,67,111,109,112,117,116,101,114,65,114,99,104,105,116,101,99,116,117,114,101,47,108,101,103,118,56,95,97,115,109,47,108,101,103,118,56,95,97,115,109,47,115,114,99,47,115,104,105,102,116,49,54,46,114,115],"byte_start":65628,"byte_end":65634,"line_start":5,"line_end":5,"column_start":5,"column_end":11},"name":"Shift0","qualname":"::shift16::Shift16::Shift0","value":"Shift16::Shift0","parent":{"krate":0,"index":256},"children":[],"decl_id":null,"docs":"","sig":null,"attributes":[]},{"kind":"TupleVariant","id":{"krate":0,"index":575},"span":{"file_name":[47,104,111,109,101,47,116,105,109,47,82,111,119,97,110,47,67,108,97,115,115,101,115,47,67,111,109,112,117,116,101,114,65,114,99,104,105,116,101,99,116,117,114,101,47,108,101,103,118,56,95,97,115,109,47,108,101,103,118,56,95,97,115,109,47,115,114,99,47,115,104,105,102,116,49,54,46,114,115],"byte_start":65644,"byte_end":65651,"line_start":6,"line_end":6,"column_start":5,"column_end":12},"name":"Shift16","qualname":"::shift16::Shift16::Shift16","value":"Shift16::Shift16","parent":{"krate":0,"index":256},"children":[],"decl_id":null,"docs":"","sig":null,"attributes":[]},{"kind":"TupleVariant","id":{"krate":0,"index":577},"span":{"file_name":[47,104,111,109,101,47,116,105,109,47,82,111,119,97,110,47,67,108,97,115,115,101,115,47,67,111,109,112,117,116,101,114,65,114,99,104,105,116,101,99,116,117,114,101,47,108,101,103,118,56,95,97,115,109,47,108,101,103,118,56,95,97,115,109,47,115,114,99,47,115,104,105,102,116,49,54,46,114,115],"byte_start":65657,"byte_end":65664,"line_start":7,"line_end":7,"column_start":5,"column_end":12},"name":"Shift32","qualname":"::shift16::Shift16::Shift32","value":"Shift16::Shift32","parent":{"krate":0,"index":256},"children":[],"decl_id":null,"docs":"","sig":null,"attributes":[]},{"kind":"TupleVariant","id":{"krate":0,"index":579},"span":{"file_name":[47,104,111,109,101,47,116,105,109,47,82,111,119,97,110,47,67,108,97,115,115,101,115,47,67,111,109,112,117,116,101,114,65,114,99,104,105,116,101,99,116,117,114,101,47,108,101,103,118,56,95,97,115,109,47,108,101,103,118,56,95,97,115,109,47,115,114,99,47,115,104,105,102,116,49,54,46,114,115],"byte_start":65670,"byte_end":65677,"line_start":8,"line_end":8,"column_start":5,"column_end":12},"name":"Shift48","qualname":"::shift16::Shift16::Shift48","value":"Shift16::Shift48","parent":{"krate":0,"index":256},"children":[],"decl_id":null,"docs":"","sig":null,"attributes":[]},{"kind":"Enum","id":{"krate":0,"index":256},"span":{"file_name":[47,104,111,109,101,47,116,105,109,47,82,111,119,97,110,47,67,108,97,115,115,101,115,47,67,111,109,112,117,116,101,114,65,114,99,104,105,116,101,99,116,117,114,101,47,108,101,103,118,56,95,97,115,109,47,108,101,103,118,56,95,97,115,109,47,115,114,99,47,115,104,105,102,116,49,54,46,114,115],"byte_start":65614,"byte_end":65621,"line_start":4,"line_end":4,"column_start":10,"column_end":17},"name":"Shift16","qualname":"::shift16::Shift16","value":"Shift16::{Shift0, Shift16, Shift32, Shift48}","parent":null,"children":[{"krate":0,"index":571},{"krate":0,"index":575},{"krate":0,"index":577},{"krate":0,"index":579}],"decl_id":null,"docs":"","sig":null,"attributes":[]},{"kind":"Mod","id":{"krate":0,"index":100},"span":{"file_name":[47,104,111,109,101,47,116,105,109,47,82,111,119,97,110,47,67,108,97,115,115,101,115,47,67,111,109,112,117,116,101,114,65,114,99,104,105,116,101,99,116,117,114,101,47,108,101,103,118,56,95,97,115,109,47,108,101,103,118,56,95,97,115,109,47,115,114,99,47,99,111,110,100,105,116,105,111,110,46,114,115],"byte_start":0,"byte_end":0,"line_start":1,"line_end":1,"column_start":1,"column_end":1},"name":"condition","qualname":"::condition","value":"/home/tim/Rowan/Classes/ComputerArchitecture/legv8_asm/legv8_asm/src/condition.rs","parent":null,"children":[{"krate":0,"index":102},{"krate":0,"index":266},{"krate":0,"index":272},{"krate":0,"index":268},{"krate":0,"index":104}],"decl_id":null,"docs":"","sig":null,"attributes":[]},{"kind":"TupleVariant","id":{"krate":0,"index":581},"span":{"file_name":[47,104,111,109,101,47,116,105,109,47,82,111,119,97,110,47,67,108,97,115,115,101,115,47,67,111,109,112,117,116,101,114,65,114,99,104,105,116,101,99,116,117,114,101,47,108,101,103,118,56,95,97,115,109,47,108,101,103,118,56,95,97,115,109,47,115,114,99,47,99,111,110,100,105,116,105,111,110,46,114,115],"byte_start":66270,"byte_end":66275,"line_start":5,"line_end":5,"column_start":5,"column_end":10},"name":"Equal","qualname":"::condition::Condition::Equal","value":"Condition::Equal","parent":{"krate":0,"index":266},"children":[],"decl_id":null,"docs":"","sig":null,"attributes":[]},{"kind":"TupleVariant","id":{"krate":0,"index":585},"span":{"file_name":[47,104,111,109,101,47,116,105,109,47,82,111,119,97,110,47,67,108,97,115,115,101,115,47,67,111,109,112,117,116,101,114,65,114,99,104,105,116,101,99,116,117,114,101,47,108,101,103,118,56,95,97,115,109,47,108,101,103,118,56,95,97,115,109,47,115,114,99,47,99,111,110,100,105,116,105,111,110,46,114,115],"byte_start":66285,"byte_end":66293,"line_start":6,"line_end":6,"column_start":5,"column_end":13},"name":"NotEqual","qualname":"::condition::Condition::NotEqual","value":"Condition::NotEqual","parent":{"krate":0,"index":266},"children":[],"decl_id":null,"docs":"","sig":null,"attributes":[]},{"kind":"TupleVariant","id":{"krate":0,"index":587},"span":{"file_name":[47,104,111,109,101,47,116,105,109,47,82,111,119,97,110,47,67,108,97,115,115,101,115,47,67,111,109,112,117,116,101,114,65,114,99,104,105,116,101,99,116,117,114,101,47,108,101,103,118,56,95,97,115,109,47,108,101,103,118,56,95,97,115,109,47,115,114,99,47,99,111,110,100,105,116,105,111,110,46,114,115],"byte_start":66299,"byte_end":66309,"line_start":7,"line_end":7,"column_start":5,"column_end":15},"name":"HigherSame","qualname":"::condition::Condition::HigherSame","value":"Condition::HigherSame","parent":{"krate":0,"index":266},"children":[],"decl_id":null,"docs":"","sig":null,"attributes":[]},{"kind":"TupleVariant","id":{"krate":0,"index":589},"span":{"file_name":[47,104,111,109,101,47,116,105,109,47,82,111,119,97,110,47,67,108,97,115,115,101,115,47,67,111,109,112,117,116,101,114,65,114,99,104,105,116,101,99,116,117,114,101,47,108,101,103,118,56,95,97,115,109,47,108,101,103,118,56,95,97,115,109,47,115,114,99,47,99,111,110,100,105,116,105,111,110,46,114,115],"byte_start":66315,"byte_end":66320,"line_start":8,"line_end":8,"column_start":5,"column_end":10},"name":"Lower","qualname":"::condition::Condition::Lower","value":"Condition::Lower","parent":{"krate":0,"index":266},"children":[],"decl_id":null,"docs":"","sig":null,"attributes":[]},{"kind":"TupleVariant","id":{"krate":0,"index":591},"span":{"file_name":[47,104,111,109,101,47,116,105,109,47,82,111,119,97,110,47,67,108,97,115,115,101,115,47,67,111,109,112,117,116,101,114,65,114,99,104,105,116,101,99,116,117,114,101,47,108,101,103,118,56,95,97,115,109,47,108,101,103,118,56,95,97,115,109,47,115,114,99,47,99,111,110,100,105,116,105,111,110,46,114,115],"byte_start":66326,"byte_end":66331,"line_start":9,"line_end":9,"column_start":5,"column_end":10},"name":"Minus","qualname":"::condition::Condition::Minus","value":"Condition::Minus","parent":{"krate":0,"index":266},"children":[],"decl_id":null,"docs":"","sig":null,"attributes":[]},{"kind":"TupleVariant","id":{"krate":0,"index":593},"span":{"file_name":[47,104,111,109,101,47,116,105,109,47,82,111,119,97,110,47,67,108,97,115,115,101,115,47,67,111,109,112,117,116,101,114,65,114,99,104,105,116,101,99,116,117,114,101,47,108,101,103,118,56,95,97,115,109,47,108,101,103,118,56,95,97,115,109,47,115,114,99,47,99,111,110,100,105,116,105,111,110,46,114,115],"byte_start":66337,"byte_end":66349,"line_start":10,"line_end":10,"column_start":5,"column_end":17},"name":"PositiveZero","qualname":"::condition::Condition::PositiveZero","value":"Condition::PositiveZero","parent":{"krate":0,"index":266},"children":[],"decl_id":null,"docs":"","sig":null,"attributes":[]},{"kind":"TupleVariant","id":{"krate":0,"index":595},"span":{"file_name":[47,104,111,109,101,47,116,105,109,47,82,111,119,97,110,47,67,108,97,115,115,101,115,47,67,111,109,112,117,116,101,114,65,114,99,104,105,116,101,99,116,117,114,101,47,108,101,103,118,56,95,97,115,109,47,108,101,103,118,56,95,97,115,109,47,115,114,99,47,99,111,110,100,105,116,105,111,110,46,114,115],"byte_start":66355,"byte_end":66369,"line_start":11,"line_end":11,"column_start":5,"column_end":19},"name":"SignedOverflow","qualname":"::condition::Condition::SignedOverflow","value":"Condition::SignedOverflow","parent":{"krate":0,"index":266},"children":[],"decl_id":null,"docs":"","sig":null,"attributes":[]},{"kind":"TupleVariant","id":{"krate":0,"index":597},"span":{"file_name":[47,104,111,109,101,47,116,105,109,47,82,111,119,97,110,47,67,108,97,115,115,101,115,47,67,111,109,112,117,116,101,114,65,114,99,104,105,116,101,99,116,117,114,101,47,108,101,103,118,56,95,97,115,109,47,108,101,103,118,56,95,97,115,109,47,115,114,99,47,99,111,110,100,105,116,105,111,110,46,114,115],"byte_start":66375,"byte_end":66391,"line_start":12,"line_end":12,"column_start":5,"column_end":21},"name":"NoSignedOverflow","qualname":"::condition::Condition::NoSignedOverflow","value":"Condition::NoSignedOverflow","parent":{"krate":0,"index":266},"children":[],"decl_id":null,"docs":"","sig":null,"attributes":[]},{"kind":"TupleVariant","id":{"krate":0,"index":599},"span":{"file_name":[47,104,111,109,101,47,116,105,109,47,82,111,119,97,110,47,67,108,97,115,115,101,115,47,67,111,109,112,117,116,101,114,65,114,99,104,105,116,101,99,116,117,114,101,47,108,101,103,118,56,95,97,115,109,47,108,101,103,118,56,95,97,115,109,47,115,114,99,47,99,111,110,100,105,116,105,111,110,46,114,115],"byte_start":66397,"byte_end":66403,"line_start":13,"line_end":13,"column_start":5,"column_end":11},"name":"Higher","qualname":"::condition::Condition::Higher","value":"Condition::Higher","parent":{"krate":0,"index":266},"children":[],"decl_id":null,"docs":"","sig":null,"attributes":[]},{"kind":"TupleVariant","id":{"krate":0,"index":601},"span":{"file_name":[47,104,111,109,101,47,116,105,109,47,82,111,119,97,110,47,67,108,97,115,115,101,115,47,67,111,109,112,117,116,101,114,65,114,99,104,105,116,101,99,116,117,114,101,47,108,101,103,118,56,95,97,115,109,47,108,101,103,118,56,95,97,115,109,47,115,114,99,47,99,111,110,100,105,116,105,111,110,46,114,115],"byte_start":66409,"byte_end":66418,"line_start":14,"line_end":14,"column_start":5,"column_end":14},"name":"LowerSame","qualname":"::condition::Condition::LowerSame","value":"Condition::LowerSame","parent":{"krate":0,"index":266},"children":[],"decl_id":null,"docs":"","sig":null,"attributes":[]},{"kind":"TupleVariant","id":{"krate":0,"index":603},"span":{"file_name":[47,104,111,109,101,47,116,105,109,47,82,111,119,97,110,47,67,108,97,115,115,101,115,47,67,111,109,112,117,116,101,114,65,114,99,104,105,116,101,99,116,117,114,101,47,108,101,103,118,56,95,97,115,109,47,108,101,103,118,56,95,97,115,109,47,115,114,99,47,99,111,110,100,105,116,105,111,110,46,114,115],"byte_start":66424,"byte_end":66440,"line_start":15,"line_end":15,"column_start":5,"column_end":21},"name":"GreaterThanEqual","qualname":"::condition::Condition::GreaterThanEqual","value":"Condition::GreaterThanEqual","parent":{"krate":0,"index":266},"children":[],"decl_id":null,"docs":"","sig":null,"attributes":[]},{"kind":"TupleVariant","id":{"krate":0,"index":605},"span":{"file_name":[47,104,111,109,101,47,116,105,109,47,82,111,119,97,110,47,67,108,97,115,115,101,115,47,67,111,109,112,117,116,101,114,65,114,99,104,105,116,101,99,116,117,114,101,47,108,101,103,118,56,95,97,115,109,47,108,101,103,118,56,95,97,115,109,47,115,114,99,47,99,111,110,100,105,116,105,111,110,46,114,115],"byte_start":66446,"byte_end":66454,"line_start":16,"line_end":16,"column_start":5,"column_end":13},"name":"LessThan","qualname":"::condition::Condition::LessThan","value":"Condition::LessThan","parent":{"krate":0,"index":266},"children":[],"decl_id":null,"docs":"","sig":null,"attributes":[]},{"kind":"TupleVariant","id":{"krate":0,"index":607},"span":{"file_name":[47,104,111,109,101,47,116,105,109,47,82,111,119,97,110,47,67,108,97,115,115,101,115,47,67,111,109,112,117,116,101,114,65,114,99,104,105,116,101,99,116,117,114,101,47,108,101,103,118,56,95,97,115,109,47,108,101,103,118,56,95,97,115,109,47,115,114,99,47,99,111,110,100,105,116,105,111,110,46,114,115],"byte_start":66460,"byte_end":66471,"line_start":17,"line_end":17,"column_start":5,"column_end":16},"name":"GreaterThan","qualname":"::condition::Condition::GreaterThan","value":"Condition::GreaterThan","parent":{"krate":0,"index":266},"children":[],"decl_id":null,"docs":"","sig":null,"attributes":[]},{"kind":"TupleVariant","id":{"krate":0,"index":609},"span":{"file_name":[47,104,111,109,101,47,116,105,109,47,82,111,119,97,110,47,67,108,97,115,115,101,115,47,67,111,109,112,117,116,101,114,65,114,99,104,105,116,101,99,116,117,114,101,47,108,101,103,118,56,95,97,115,109,47,108,101,103,118,56,95,97,115,109,47,115,114,99,47,99,111,110,100,105,116,105,111,110,46,114,115],"byte_start":66477,"byte_end":66490,"line_start":18,"line_end":18,"column_start":5,"column_end":18},"name":"LessThanEqual","qualname":"::condition::Condition::LessThanEqual","value":"Condition::LessThanEqual","parent":{"krate":0,"index":266},"children":[],"decl_id":null,"docs":"","sig":null,"attributes":[]},{"kind":"TupleVariant","id":{"krate":0,"index":611},"span":{"file_name":[47,104,111,109,101,47,116,105,109,47,82,111,119,97,110,47,67,108,97,115,115,101,115,47,67,111,109,112,117,116,101,114,65,114,99,104,105,116,101,99,116,117,114,101,47,108,101,103,118,56,95,97,115,109,47,108,101,103,118,56,95,97,115,109,47,115,114,99,47,99,111,110,100,105,116,105,111,110,46,114,115],"byte_start":66496,"byte_end":66502,"line_start":19,"line_end":19,"column_start":5,"column_end":11},"name":"Always","qualname":"::condition::Condition::Always","value":"Condition::Always","parent":{"krate":0,"index":266},"children":[],"decl_id":null,"docs":"","sig":null,"attributes":[]},{"kind":"TupleVariant","id":{"krate":0,"index":613},"span":{"file_name":[47,104,111,109,101,47,116,105,109,47,82,111,119,97,110,47,67,108,97,115,115,101,115,47,67,111,109,112,117,116,101,114,65,114,99,104,105,116,101,99,116,117,114,101,47,108,101,103,118,56,95,97,115,109,47,108,101,103,118,56,95,97,115,109,47,115,114,99,47,99,111,110,100,105,116,105,111,110,46,114,115],"byte_start":66508,"byte_end":66516,"line_start":20,"line_end":20,"column_start":5,"column_end":13},"name":"Reserved","qualname":"::condition::Condition::Reserved","value":"Condition::Reserved","parent":{"krate":0,"index":266},"children":[],"decl_id":null,"docs":"","sig":null,"attributes":[]},{"kind":"Enum","id":{"krate":0,"index":266},"span":{"file_name":[47,104,111,109,101,47,116,105,109,47,82,111,119,97,110,47,67,108,97,115,115,101,115,47,67,111,109,112,117,116,101,114,65,114,99,104,105,116,101,99,116,117,114,101,47,108,101,103,118,56,95,97,115,109,47,108,101,103,118,56,95,97,115,109,47,115,114,99,47,99,111,110,100,105,116,105,111,110,46,114,115],"byte_start":66254,"byte_end":66263,"line_start":4,"line_end":4,"column_start":10,"column_end":19},"name":"Condition","qualname":"::condition::Condition","value":"Condition::{Equal, NotEqual, HigherSame, Lower, Minus, PositiveZero, SignedOverflow, NoSignedOverflow, Higher, LowerSame, GreaterThanEqual, LessThan, GreaterThan, LessThanEqual, Always, Reserved}","parent":null,"children":[{"krate":0,"index":581},{"krate":0,"index":585},{"krate":0,"index":587},{"krate":0,"index":589},{"krate":0,"index":591},{"krate":0,"index":593},{"krate":0,"index":595},{"krate":0,"index":597},{"krate":0,"index":599},{"krate":0,"index":601},{"krate":0,"index":603},{"krate":0,"index":605},{"krate":0,"index":607},{"krate":0,"index":609},{"krate":0,"index":611},{"krate":0,"index":613}],"decl_id":null,"docs":"","sig":null,"attributes":[]},{"kind":"Mod","id":{"krate":0,"index":108},"span":{"file_name":[47,104,111,109,101,47,116,105,109,47,82,111,119,97,110,47,67,108,97,115,115,101,115,47,67,111,109,112,117,116,101,114,65,114,99,104,105,116,101,99,116,117,114,101,47,108,101,103,118,56,95,97,115,109,47,108,101,103,118,56,95,97,115,109,47,115,114,99,47,105,109,109,101,100,105,97,116,101,46,114,115],"byte_start":0,"byte_end":0,"line_start":1,"line_end":1,"column_start":1,"column_end":1},"name":"immediate","qualname":"::immediate","value":"/home/tim/Rowan/Classes/ComputerArchitecture/legv8_asm/legv8_asm/src/immediate.rs","parent":null,"children":[{"krate":0,"index":110},{"krate":0,"index":276},{"krate":0,"index":284},{"krate":0,"index":278},{"krate":0,"index":112},{"krate":0,"index":116},{"krate":0,"index":288},{"krate":0,"index":296},{"krate":0,"index":290},{"krate":0,"index":120},{"krate":0,"index":124},{"krate":0,"index":300},{"krate":0,"index":308},{"krate":0,"index":302},{"krate":0,"index":128},{"krate":0,"index":132},{"krate":0,"index":312},{"krate":0,"index":320},{"krate":0,"index":314},{"krate":0,"index":136},{"krate":0,"index":140},{"krate":0,"index":324},{"krate":0,"index":332},{"krate":0,"index":326},{"krate":0,"index":144},{"krate":0,"index":148},{"krate":0,"index":336},{"krate":0,"index":344},{"krate":0,"index":338},{"krate":0,"index":152},{"krate":0,"index":156}],"decl_id":null,"docs":"","sig":null,"attributes":[]},{"kind":"Struct","id":{"krate":0,"index":276},"span":{"file_name":[47,104,111,109,101,47,116,105,109,47,82,111,119,97,110,47,67,108,97,115,115,101,115,47,67,111,109,112,117,116,101,114,65,114,99,104,105,116,101,99,116,117,114,101,47,108,101,103,118,56,95,97,115,109,47,108,101,103,118,56,95,97,115,109,47,115,114,99,47,105,109,109,101,100,105,97,116,101,46,114,115],"byte_start":67194,"byte_end":67204,"line_start":4,"line_end":4,"column_start":12,"column_end":22},"name":"Immediate6","qualname":"::immediate::Immediate6","value":"","parent":null,"children":[],"decl_id":null,"docs":"","sig":null,"attributes":[]},{"kind":"Struct","id":{"krate":0,"index":288},"span":{"file_name":[47,104,111,109,101,47,116,105,109,47,82,111,119,97,110,47,67,108,97,115,115,101,115,47,67,111,109,112,117,116,101,114,65,114,99,104,105,116,101,99,116,117,114,101,47,108,101,103,118,56,95,97,115,109,47,108,101,103,118,56,95,97,115,109,47,115,114,99,47,105,109,109,101,100,105,97,116,101,46,114,115],"byte_start":67636,"byte_end":67646,"line_start":23,"line_end":23,"column_start":12,"column_end":22},"name":"Immediate9","qualname":"::immediate::Immediate9","value":"","parent":null,"children":[],"decl_id":null,"docs":"","sig":null,"attributes":[]},{"kind":"Struct","id":{"krate":0,"index":300},"span":{"file_name":[47,104,111,109,101,47,116,105,109,47,82,111,119,97,110,47,67,108,97,115,115,101,115,47,67,111,109,112,117,116,101,114,65,114,99,104,105,116,101,99,116,117,114,101,47,108,101,103,118,56,95,97,115,109,47,108,101,103,118,56,95,97,115,109,47,115,114,99,47,105,109,109,101,100,105,97,116,101,46,114,115],"byte_start":68081,"byte_end":68092,"line_start":42,"line_end":42,"column_start":12,"column_end":23},"name":"Immediate12","qualname":"::immediate::Immediate12","value":"","parent":null,"children":[],"decl_id":null,"docs":"","sig":null,"attributes":[]},{"kind":"Struct","id":{"krate":0,"index":312},"span":{"file_name":[47,104,111,109,101,47,116,105,109,47,82,111,119,97,110,47,67,108,97,115,115,101,115,47,67,111,109,112,117,116,101,114,65,114,99,104,105,116,101,99,116,117,114,101,47,108,101,103,118,56,95,97,115,109,47,108,101,103,118,56,95,97,115,109,47,115,114,99,47,105,109,109,101,100,105,97,116,101,46,114,115],"byte_start":68537,"byte_end":68548,"line_start":61,"line_end":61,"column_start":12,"column_end":23},"name":"Immediate16","qualname":"::immediate::Immediate16","value":"","parent":null,"children":[],"decl_id":null,"docs":"","sig":null,"attributes":[]},{"kind":"Struct","id":{"krate":0,"index":324},"span":{"file_name":[47,104,111,109,101,47,116,105,109,47,82,111,119,97,110,47,67,108,97,115,115,101,115,47,67,111,109,112,117,116,101,114,65,114,99,104,105,116,101,99,116,117,114,101,47,108,101,103,118,56,95,97,115,109,47,108,101,103,118,56,95,97,115,109,47,115,114,99,47,105,109,109,101,100,105,97,116,101,46,114,115],"byte_start":68993,"byte_end":69004,"line_start":80,"line_end":80,"column_start":12,"column_end":23},"name":"Immediate19","qualname":"::immediate::Immediate19","value":"","parent":null,"children":[],"decl_id":null,"docs":"","sig":null,"attributes":[]},{"kind":"Struct","id":{"krate":0,"index":336},"span":{"file_name":[47,104,111,109,101,47,116,105,109,47,82,111,119,97,110,47,67,108,97,115,115,101,115,47,67,111,109,112,117,116,101,114,65,114,99,104,105,116,101,99,116,117,114,101,47,108,101,103,118,56,95,97,115,109,47,108,101,103,118,56,95,97,115,109,47,115,114,99,47,105,109,109,101,100,105,97,116,101,46,114,115],"byte_start":69449,"byte_end":69460,"line_start":99,"line_end":99,"column_start":12,"column_end":23},"name":"Immediate26","qualname":"::immediate::Immediate26","value":"","parent":null,"children":[],"decl_id":null,"docs":"","sig":null,"attributes":[]},{"kind":"Mod","id":{"krate":0,"index":160},"span":{"file_name":[47,104,111,109,101,47,116,105,109,47,82,111,119,97,110,47,67,108,97,115,115,101,115,47,67,111,109,112,117,116,101,114,65,114,99,104,105,116,101,99,116,117,114,101,47,108,101,103,118,56,95,97,115,109,47,108,101,103,118,56,95,97,115,109,47,115,114,99,47,103,101,110,101,114,97,116,111,114,46,114,115],"byte_start":0,"byte_end":0,"line_start":1,"line_end":1,"column_start":1,"column_end":1},"name":"generator","qualname":"::generator","value":"/home/tim/Rowan/Classes/ComputerArchitecture/legv8_asm/legv8_asm/src/generator.rs","parent":null,"children":[{"krate":0,"index":162},{"krate":0,"index":164},{"krate":0,"index":166}],"decl_id":null,"docs":"","sig":null,"attributes":[]},{"kind":"Function","id":{"krate":0,"index":164},"span":{"file_name":[47,104,111,109,101,47,116,105,109,47,82,111,119,97,110,47,67,108,97,115,115,101,115,47,67,111,109,112,117,116,101,114,65,114,99,104,105,116,101,99,116,117,114,101,47,108,101,103,118,56,95,97,115,109,47,108,101,103,118,56,95,97,115,109,47,115,114,99,47,103,101,110,101,114,97,116,111,114,46,114,115],"byte_start":69888,"byte_end":69907,"line_start":3,"line_end":3,"column_start":8,"column_end":27},"name":"generate_binary_str","qualname":"::generator::generate_binary_str","value":"fn (instructions: Vec<[Bit; 32]>) -> String","parent":null,"children":[],"decl_id":null,"docs":"","sig":null,"attributes":[]},{"kind":"Function","id":{"krate":0,"index":166},"span":{"file_name":[47,104,111,109,101,47,116,105,109,47,82,111,119,97,110,47,67,108,97,115,115,101,115,47,67,111,109,112,117,116,101,114,65,114,99,104,105,116,101,99,116,117,114,101,47,108,101,103,118,56,95,97,115,109,47,108,101,103,118,56,95,97,115,109,47,115,114,99,47,103,101,110,101,114,97,116,111,114,46,114,115],"byte_start":70502,"byte_end":70519,"line_start":25,"line_end":25,"column_start":8,"column_end":25},"name":"generate_case_rom","qualname":"::generator::generate_case_rom","value":"fn (instructions: Vec<[Bit; 32]>) -> String","parent":null,"children":[],"decl_id":null,"docs":"","sig":null,"attributes":[]},{"kind":"Function","id":{"krate":0,"index":170},"span":{"file_name":[47,104,111,109,101,47,116,105,109,47,82,111,119,97,110,47,67,108,97,115,115,101,115,47,67,111,109,112,117,116,101,114,65,114,99,104,105,116,101,99,116,117,114,101,47,108,101,103,118,56,95,97,115,109,47,108,101,103,118,56,95,97,115,109,47,115,114,99,47,108,105,98,46,114,115],"byte_start":224,"byte_end":236,"line_start":18,"line_end":18,"column_start":8,"column_end":20},"name":"parse_to_rom","qualname":"::parse_to_rom","value":"fn (assembly: &str) -> String","parent":null,"children":[],"decl_id":null,"docs":"","sig":null,"attributes":[{"value":"no_mangle","span":{"file_name":[47,104,111,109,101,47,116,105,109,47,82,111,119,97,110,47,67,108,97,115,115,101,115,47,67,111,109,112,117,116,101,114,65,114,99,104,105,116,101,99,116,117,114,101,47,108,101,103,118,56,95,97,115,109,47,108,101,103,118,56,95,97,115,109,47,115,114,99,47,108,105,98,46,114,115],"byte_start":204,"byte_end":216,"line_start":17,"line_end":17,"column_start":1,"column_end":13}}]}],"impls":[{"id":0,"kind":"Inherent","span":{"file_name":[47,104,111,109,101,47,116,105,109,47,82,111,119,97,110,47,67,108,97,115,115,101,115,47,67,111,109,112,117,116,101,114,65,114,99,104,105,116,101,99,116,117,114,101,47,108,101,103,118,56,95,97,115,109,47,108,101,103,118,56,95,97,115,109,47,115,114,99,47,98,105,116,46,114,115],"byte_start":1687,"byte_end":1690,"line_start":9,"line_end":9,"column_start":6,"column_end":9},"value":"","parent":null,"children":[{"krate":0,"index":12},{"krate":0,"index":14}],"docs":"","sig":null,"attributes":[]},{"id":3,"kind":"Direct","span":{"file_name":[47,104,111,109,101,47,116,105,109,47,82,111,119,97,110,47,67,108,97,115,115,101,115,47,67,111,109,112,117,116,101,114,65,114,99,104,105,116,101,99,116,117,114,101,47,108,101,103,118,56,95,97,115,109,47,108,101,103,118,56,95,97,115,109,47,115,114,99,47,105,109,109,101,100,105,97,116,101,46,114,115],"byte_start":67233,"byte_end":67243,"line_start":6,"line_end":6,"column_start":19,"column_end":29},"value":"","parent":null,"children":[{"krate":0,"index":114}],"docs":"","sig":null,"attributes":[]},{"id":4,"kind":"Direct","span":{"file_name":[47,104,111,109,101,47,116,105,109,47,82,111,119,97,110,47,67,108,97,115,115,101,115,47,67,111,109,112,117,116,101,114,65,114,99,104,105,116,101,99,116,117,114,101,47,108,101,103,118,56,95,97,115,109,47,108,101,103,118,56,95,97,115,109,47,115,114,99,47,105,109,109,101,100,105,97,116,101,46,114,115],"byte_start":67677,"byte_end":67687,"line_start":25,"line_end":25,"column_start":20,"column_end":30},"value":"","parent":null,"children":[{"krate":0,"index":122}],"docs":"","sig":null,"attributes":[]},{"id":5,"kind":"Direct","span":{"file_name":[47,104,111,109,101,47,116,105,109,47,82,111,119,97,110,47,67,108,97,115,115,101,115,47,67,111,109,112,117,116,101,114,65,114,99,104,105,116,101,99,116,117,114,101,47,108,101,103,118,56,95,97,115,109,47,108,101,103,118,56,95,97,115,109,47,115,114,99,47,105,109,109,101,100,105,97,116,101,46,114,115],"byte_start":68123,"byte_end":68134,"line_start":44,"line_end":44,"column_start":20,"column_end":31},"value":"","parent":null,"children":[{"krate":0,"index":130}],"docs":"","sig":null,"attributes":[]},{"id":6,"kind":"Direct","span":{"file_name":[47,104,111,109,101,47,116,105,109,47,82,111,119,97,110,47,67,108,97,115,115,101,115,47,67,111,109,112,117,116,101,114,65,114,99,104,105,116,101,99,116,117,114,101,47,108,101,103,118,56,95,97,115,109,47,108,101,103,118,56,95,97,115,109,47,115,114,99,47,105,109,109,101,100,105,97,116,101,46,114,115],"byte_start":68579,"byte_end":68590,"line_start":63,"line_end":63,"column_start":20,"column_end":31},"value":"","parent":null,"children":[{"krate":0,"index":138}],"docs":"","sig":null,"attributes":[]},{"id":7,"kind":"Direct","span":{"file_name":[47,104,111,109,101,47,116,105,109,47,82,111,119,97,110,47,67,108,97,115,115,101,115,47,67,111,109,112,117,116,101,114,65,114,99,104,105,116,101,99,116,117,114,101,47,108,101,103,118,56,95,97,115,109,47,108,101,103,118,56,95,97,115,109,47,115,114,99,47,105,109,109,101,100,105,97,116,101,46,114,115],"byte_start":69035,"byte_end":69046,"line_start":82,"line_end":82,"column_start":20,"column_end":31},"value":"","parent":null,"children":[{"krate":0,"index":146}],"docs":"","sig":null,"attributes":[]},{"id":8,"kind":"Direct","span":{"file_name":[47,104,111,109,101,47,116,105,109,47,82,111,119,97,110,47,67,108,97,115,115,101,115,47,67,111,109,112,117,116,101,114,65,114,99,104,105,116,101,99,116,117,114,101,47,108,101,103,118,56,95,97,115,109,47,108,101,103,118,56,95,97,115,109,47,115,114,99,47,105,109,109,101,100,105,97,116,101,46,114,115],"byte_start":69491,"byte_end":69502,"line_start":101,"line_end":101,"column_start":20,"column_end":31},"value":"","parent":null,"children":[{"krate":0,"index":154}],"docs":"","sig":null,"attributes":[]}],"refs":[{"kind":"Mod","span":{"file_name":[47,104,111,109,101,47,116,105,109,47,82,111,119,97,110,47,67,108,97,115,115,101,115,47,67,111,109,112,117,116,101,114,65,114,99,104,105,116,101,99,116,117,114,101,47,108,101,103,118,56,95,97,115,109,47,108,101,103,118,56,95,97,115,109,47,115,114,99,47,108,105,98,46,114,115],"byte_start":54,"byte_end":57,"line_start":6,"line_end":6,"column_start":9,"column_end":12},"ref_id":{"krate":0,"index":8}},{"kind":"Mod","span":{"file_name":[47,104,111,109,101,47,116,105,109,47,82,111,119,97,110,47,67,108,97,115,115,101,115,47,67,111,109,112,117,116,101,114,65,114,99,104,105,116,101,99,116,117,114,101,47,108,101,103,118,56,95,97,115,109,47,108,101,103,118,56,95,97,115,109,47,115,114,99,47,108,105,98,46,114,115],"byte_start":67,"byte_end":78,"line_start":7,"line_end":7,"column_start":9,"column_end":20},"ref_id":{"krate":0,"index":26}},{"kind":"Mod","span":{"file_name":[47,104,111,109,101,47,116,105,109,47,82,111,119,97,110,47,67,108,97,115,115,101,115,47,67,111,109,112,117,116,101,114,65,114,99,104,105,116,101,99,116,117,114,101,47,108,101,103,118,56,95,97,115,109,47,108,101,103,118,56,95,97,115,109,47,115,114,99,47,108,105,98,46,114,115],"byte_start":88,"byte_end":94,"line_start":8,"line_end":8,"column_start":9,"column_end":15},"ref_id":{"krate":0,"index":52}},{"kind":"Mod","span":{"file_name":[47,104,111,109,101,47,116,105,109,47,82,111,119,97,110,47,67,108,97,115,115,101,115,47,67,111,109,112,117,116,101,114,65,114,99,104,105,116,101,99,116,117,114,101,47,108,101,103,118,56,95,97,115,109,47,108,101,103,118,56,95,97,115,109,47,115,114,99,47,108,105,98,46,114,115],"byte_start":104,"byte_end":112,"line_start":9,"line_end":9,"column_start":9,"column_end":17},"ref_id":{"krate":0,"index":84}},{"kind":"Mod","span":{"file_name":[47,104,111,109,101,47,116,105,109,47,82,111,119,97,110,47,67,108,97,115,115,101,115,47,67,111,109,112,117,116,101,114,65,114,99,104,105,116,101,99,116,117,114,101,47,108,101,103,118,56,95,97,115,109,47,108,101,103,118,56,95,97,115,109,47,115,114,99,47,108,105,98,46,114,115],"byte_start":122,"byte_end":129,"line_start":10,"line_end":10,"column_start":9,"column_end":16},"ref_id":{"krate":0,"index":92}},{"kind":"Mod","span":{"file_name":[47,104,111,109,101,47,116,105,109,47,82,111,119,97,110,47,67,108,97,115,115,101,115,47,67,111,109,112,117,116,101,114,65,114,99,104,105,116,101,99,116,117,114,101,47,108,101,103,118,56,95,97,115,109,47,108,101,103,118,56,95,97,115,109,47,115,114,99,47,108,105,98,46,114,115],"byte_start":139,"byte_end":148,"line_start":11,"line_end":11,"column_start":9,"column_end":18},"ref_id":{"krate":0,"index":100}},{"kind":"Mod","span":{"file_name":[47,104,111,109,101,47,116,105,109,47,82,111,119,97,110,47,67,108,97,115,115,101,115,47,67,111,109,112,117,116,101,114,65,114,99,104,105,116,101,99,116,117,114,101,47,108,101,103,118,56,95,97,115,109,47,108,101,103,118,56,95,97,115,109,47,115,114,99,47,108,105,98,46,114,115],"byte_start":158,"byte_end":167,"line_start":12,"line_end":12,"column_start":9,"column_end":18},"ref_id":{"krate":0,"index":108}},{"kind":"Mod","span":{"file_name":[47,104,111,109,101,47,116,105,109,47,82,111,119,97,110,47,67,108,97,115,115,101,115,47,67,111,109,112,117,116,101,114,65,114,99,104,105,116,101,99,116,117,114,101,47,108,101,103,118,56,95,97,115,109,47,108,101,103,118,56,95,97,115,109,47,115,114,99,47,108,105,98,46,114,115],"byte_start":177,"byte_end":186,"line_start":13,"line_end":13,"column_start":9,"column_end":18},"ref_id":{"krate":0,"index":160}}],"macro_refs":[],"relations":[{"span":{"file_name":[47,104,111,109,101,47,116,105,109,47,82,111,119,97,110,47,67,108,97,115,115,101,115,47,67,111,109,112,117,116,101,114,65,114,99,104,105,116,101,99,116,117,114,101,47,108,101,103,118,56,95,97,115,109,47,108,101,103,118,56,95,97,115,109,47,115,114,99,47,98,105,116,46,114,115],"byte_start":1687,"byte_end":1690,"line_start":9,"line_end":9,"column_start":6,"column_end":9},"kind":{"variant":"Impl","fields":[0]},"from":{"krate":0,"index":172},"to":{"krate":4294967295,"index":4294967295}},{"span":{"file_name":[47,104,111,109,101,47,116,105,109,47,82,111,119,97,110,47,67,108,97,115,115,101,115,47,67,111,109,112,117,116,101,114,65,114,99,104,105,116,101,99,116,117,114,101,47,108,101,103,118,56,95,97,115,109,47,108,101,103,118,56,95,97,115,109,47,115,114,99,47,105,109,109,101,100,105,97,116,101,46,114,115],"byte_start":67233,"byte_end":67243,"line_start":6,"line_end":6,"column_start":19,"column_end":29},"kind":{"variant":"Impl","fields":[3]},"from":{"krate":0,"index":276},"to":{"krate":2,"index":2548}},{"span":{"file_name":[47,104,111,109,101,47,116,105,109,47,82,111,119,97,110,47,67,108,97,115,115,101,115,47,67,111,109,112,117,116,101,114,65,114,99,104,105,116,101,99,116,117,114,101,47,108,101,103,118,56,95,97,115,109,47,108,101,103,118,56,95,97,115,109,47,115,114,99,47,105,109,109,101,100,105,97,116,101,46,114,115],"byte_start":67677,"byte_end":67687,"line_start":25,"line_end":25,"column_start":20,"column_end":30},"kind":{"variant":"Impl","fields":[4]},"from":{"krate":0,"index":288},"to":{"krate":2,"index":2548}},{"span":{"file_name":[47,104,111,109,101,47,116,105,109,47,82,111,119,97,110,47,67,108,97,115,115,101,115,47,67,111,109,112,117,116,101,114,65,114,99,104,105,116,101,99,116,117,114,101,47,108,101,103,118,56,95,97,115,109,47,108,101,103,118,56,95,97,115,109,47,115,114,99,47,105,109,109,101,100,105,97,116,101,46,114,115],"byte_start":68123,"byte_end":68134,"line_start":44,"line_end":44,"column_start":20,"column_end":31},"kind":{"variant":"Impl","fields":[5]},"from":{"krate":0,"index":300},"to":{"krate":2,"index":2548}},{"span":{"file_name":[47,104,111,109,101,47,116,105,109,47,82,111,119,97,110,47,67,108,97,115,115,101,115,47,67,111,109,112,117,116,101,114,65,114,99,104,105,116,101,99,116,117,114,101,47,108,101,103,118,56,95,97,115,109,47,108,101,103,118,56,95,97,115,109,47,115,114,99,47,105,109,109,101,100,105,97,116,101,46,114,115],"byte_start":68579,"byte_end":68590,"line_start":63,"line_end":63,"column_start":20,"column_end":31},"kind":{"variant":"Impl","fields":[6]},"from":{"krate":0,"index":312},"to":{"krate":2,"index":2548}},{"span":{"file_name":[47,104,111,109,101,47,116,105,109,47,82,111,119,97,110,47,67,108,97,115,115,101,115,47,67,111,109,112,117,116,101,114,65,114,99,104,105,116,101,99,116,117,114,101,47,108,101,103,118,56,95,97,115,109,47,108,101,103,118,56,95,97,115,109,47,115,114,99,47,105,109,109,101,100,105,97,116,101,46,114,115],"byte_start":69035,"byte_end":69046,"line_start":82,"line_end":82,"column_start":20,"column_end":31},"kind":{"variant":"Impl","fields":[7]},"from":{"krate":0,"index":324},"to":{"krate":2,"index":2548}},{"span":{"file_name":[47,104,111,109,101,47,116,105,109,47,82,111,119,97,110,47,67,108,97,115,115,101,115,47,67,111,109,112,117,116,101,114,65,114,99,104,105,116,101,99,116,117,114,101,47,108,101,103,118,56,95,97,115,109,47,108,101,103,118,56,95,97,115,109,47,115,114,99,47,105,109,109,101,100,105,97,116,101,46,114,115],"byte_start":69491,"byte_end":69502,"line_start":101,"line_end":101,"column_start":20,"column_end":31},"kind":{"variant":"Impl","fields":[8]},"from":{"krate":0,"index":336},"to":{"krate":2,"index":2548}}]}